[{"agent_name": "NoBackRandom", "maze_size": 21, "seed": 9216, "phase": "train", "episode": 0, "reward": -427.5600000000131, "steps": 1764, "solved": false, "synops": 0, "wall_time_s": 0.02810072898864746, "config": {"num_train": 100, "num_test": 50, "max_steps": 1764, "reward_shaping": true, "visit_penalty": true, "wall_bump_cost": -0.3, "hazard_cost": -1.0, "goal_reward": 10.0, "code_hash": "fe0b8142940e55de"}, "lib_version": "v2"}, {"agent_name": "NoBackRandom", "maze_size": 21, "seed": 9216, "phase": "train", "episode": 1, "reward": -386.5400000000113, "steps": 1764, "solved": false, "synops": 0, "wall_time_s": 0.034185171127319336, "config": {"num_train": 100, "num_test": 50, "max_steps": 1764, "reward_shaping": true, "visit_penalty": true, "wall_bump_cost": -0.3, "hazard_cost": -1.0, "goal_reward": 10.0, "code_hash": "fe0b8142940e55de"}, "lib_version": "v2"}, {"agent_name": "NoBackRandom", "maze_size": 21, "seed": 9216, "phase": "train", "episode": 2, "reward": -407.76000000001085, "steps": 1764, "solved": false, "synops": 0, "wall_time_s": 0.022724390029907227, "config": {"num_train": 100, "num_test": 50, "max_steps": 1764, "reward_shaping": true, "visit_penalty": true, "wall_bump_cost": -0.3, "hazard_cost": -1.0, "goal_reward": 10.0, "code_hash": "fe0b8142940e55de"}, "lib_version": "v2"}, {"agent_name": "NoBackRandom", "maze_size": 21, "seed": 9216, "phase": "train", "episode": 3, "reward": -366.88000000001034, "steps": 1764, "solved": false, "synops": 0, "wall_time_s": 0.03795790672302246, "config": {"num_train": 100, "num_test": 50, "max_steps": 1764, "reward_shaping": true, "visit_penalty": true, "wall_bump_cost": -0.3, "hazard_cost": -1.0, "goal_reward": 10.0, "code_hash": "fe0b8142940e55de"}, "lib_version": "v2"}, {"agent_name": "NoBackRandom", "maze_size": 21, "seed": 9216, "phase": "train", "episode": 4, "reward": -399.240000000012, "steps": 1764, "solved": false, "synops": 0, "wall_time_s": 0.026117324829101562, "config": {"num_train": 100, "num_test": 50, "max_steps": 1764, "reward_shaping": true, "visit_penalty": true, "wall_bump_cost": -0.3, "hazard_cost": -1.0, "goal_reward": 10.0, "code_hash": "fe0b8142940e55de"}, "lib_version": "v2"}, {"agent_name": "NoBackRandom", "maze_size": 21, "seed": 9216, "phase": "train", "episode": 5, "reward": -380.920000000011, "steps": 1764, "solved": false, "synops": 0, "wall_time_s": 0.024202823638916016, "config": {"num_train": 100, "num_test": 50, "max_steps": 1764, "reward_shaping": true, "visit_penalty": true, "wall_bump_cost": -0.3, "hazard_cost": -1.0, "goal_reward": 10.0, "code_hash": "fe0b8142940e55de"}, "lib_version": "v2"}, {"agent_name": "NoBackRandom", "maze_size": 21, "seed": 9216, "phase": "train", "episode": 6, "reward": -382.5000000000108, "steps": 1764, "solved": false, "synops": 0, "wall_time_s": 0.02139759063720703, "config": {"num_train": 100, "num_test": 50, "max_steps": 1764, "reward_shaping": true, "visit_penalty": true, "wall_bump_cost": -0.3, "hazard_cost": -1.0, "goal_reward": 10.0, "code_hash": "fe0b8142940e55de"}, "lib_version": "v2"}, {"agent_name": "NoBackRandom", "maze_size": 21, "seed": 9216, "phase": "train", "episode": 7, "reward": -403.4000000000106, "steps": 1764, "solved": false, "synops": 0, "wall_time_s": 0.013891220092773438, "config": {"num_train": 100, "num_test": 50, "max_steps": 1764, "reward_shaping": true, "visit_penalty": true, "wall_bump_cost": -0.3, "hazard_cost": -1.0, "goal_reward": 10.0, "code_hash": "fe0b8142940e55de"}, "lib_version": "v2"}, {"agent_name": "NoBackRandom", "maze_size": 21, "seed": 9216, "phase": "train", "episode": 8, "reward": -394.0800000000112, "steps": 1764, "solved": false, "synops": 0, "wall_time_s": 0.030627012252807617, "config": {"num_train": 100, "num_test": 50, "max_steps": 1764, "reward_shaping": true, "visit_penalty": true, "wall_bump_cost": -0.3, "hazard_cost": -1.0, "goal_reward": 10.0, "code_hash": "fe0b8142940e55de"}, "lib_version": "v2"}, {"agent_name": "NoBackRandom", "maze_size": 21, "seed": 9216, "phase": "train", "episode": 9, "reward": -397.4600000000114, "steps": 1764, "solved": false, "synops": 0, "wall_time_s": 0.0210874080657959, "config": {"num_train": 100, "num_test": 50, "max_steps": 1764, "reward_shaping": true, "visit_penalty": true, "wall_bump_cost": -0.3, "hazard_cost": -1.0, "goal_reward": 10.0, "code_hash": "fe0b8142940e55de"}, "lib_version": "v2"}, {"agent_name": "NoBackRandom", "maze_size": 21, "seed": 9216, "phase": "train", "episode": 10, "reward": -403.600000000012, "steps": 1764, "solved": false, "synops": 0, "wall_time_s": 0.0234372615814209, "config": {"num_train": 100, "num_test": 50, "max_steps": 1764, "reward_shaping": true, "visit_penalty": true, "wall_bump_cost": -0.3, "hazard_cost": -1.0, "goal_reward": 10.0, "code_hash": "fe0b8142940e55de"}, "lib_version": "v2"}, {"agent_name": "NoBackRandom", "maze_size": 21, "seed": 9216, "phase": "train", "episode": 11, "reward": -395.1800000000126, "steps": 1764, "solved": false, "synops": 0, "wall_time_s": 0.022747516632080078, "config": {"num_train": 100, "num_test": 50, "max_steps": 1764, "reward_shaping": true, "visit_penalty": true, "wall_bump_cost": -0.3, "hazard_cost": -1.0, "goal_reward": 10.0, "code_hash": "fe0b8142940e55de"}, "lib_version": "v2"}, {"agent_name": "NoBackRandom", "maze_size": 21, "seed": 9216, "phase": "train", "episode": 12, "reward": -514.8800000000147, "steps": 1764, "solved": false, "synops": 0, "wall_time_s": 0.0192263126373291, "config": {"num_train": 100, "num_test": 50, "max_steps": 1764, "reward_shaping": true, "visit_penalty": true, "wall_bump_cost": -0.3, "hazard_cost": -1.0, "goal_reward": 10.0, "code_hash": "fe0b8142940e55de"}, "lib_version": "v2"}, {"agent_name": "NoBackRandom", "maze_size": 21, "seed": 9216, "phase": "train", "episode": 13, "reward": -424.80000000001274, "steps": 1764, "solved": false, "synops": 0, "wall_time_s": 0.021466970443725586, "config": {"num_train": 100, "num_test": 50, "max_steps": 1764, "reward_shaping": true, "visit_penalty": true, "wall_bump_cost": -0.3, "hazard_cost": -1.0, "goal_reward": 10.0, "code_hash": "fe0b8142940e55de"}, "lib_version": "v2"}, {"agent_name": "NoBackRandom", "maze_size": 21, "seed": 9216, "phase": "train", "episode": 14, "reward": -409.440000000012, "steps": 1764, "solved": false, "synops": 0, "wall_time_s": 0.017877578735351562, "config": {"num_train": 100, "num_test": 50, "max_steps": 1764, "reward_shaping": true, "visit_penalty": true, "wall_bump_cost": -0.3, "hazard_cost": -1.0, "goal_reward": 10.0, "code_hash": "fe0b8142940e55de"}, "lib_version": "v2"}, {"agent_name": "NoBackRandom", "maze_size": 21, "seed": 9216, "phase": "train", "episode": 15, "reward": -377.10000000001054, "steps": 1764, "solved": false, "synops": 0, "wall_time_s": 0.024416685104370117, "config": {"num_train": 100, "num_test": 50, "max_steps": 1764, "reward_shaping": true, "visit_penalty": true, "wall_bump_cost": -0.3, "hazard_cost": -1.0, "goal_reward": 10.0, "code_hash": "fe0b8142940e55de"}, "lib_version": "v2"}, {"agent_name": "NoBackRandom", "maze_size": 21, "seed": 9216, "phase": "train", "episode": 16, "reward": -418.12000000001194, "steps": 1764, "solved": false, "synops": 0, "wall_time_s": 0.020430803298950195, "config": {"num_train": 100, "num_test": 50, "max_steps": 1764, "reward_shaping": true, "visit_penalty": true, "wall_bump_cost": -0.3, "hazard_cost": -1.0, "goal_reward": 10.0, "code_hash": "fe0b8142940e55de"}, "lib_version": "v2"}, {"agent_name": "NoBackRandom", "maze_size": 21, "seed": 9216, "phase": "train", "episode": 17, "reward": -386.70000000001124, "steps": 1764, "solved": false, "synops": 0, "wall_time_s": 0.01600337028503418, "config": {"num_train": 100, "num_test": 50, "max_steps": 1764, "reward_shaping": true, "visit_penalty": true, "wall_bump_cost": -0.3, "hazard_cost": -1.0, "goal_reward": 10.0, "code_hash": "fe0b8142940e55de"}, "lib_version": "v2"}, {"agent_name": "NoBackRandom", "maze_size": 21, "seed": 9216, "phase": "train", "episode": 18, "reward": -389.90000000001135, "steps": 1764, "solved": false, "synops": 0, "wall_time_s": 0.02385425567626953, "config": {"num_train": 100, "num_test": 50, "max_steps": 1764, "reward_shaping": true, "visit_penalty": true, "wall_bump_cost": -0.3, "hazard_cost": -1.0, "goal_reward": 10.0, "code_hash": "fe0b8142940e55de"}, "lib_version": "v2"}, {"agent_name": "NoBackRandom", "maze_size": 21, "seed": 9216, "phase": "train", "episode": 19, "reward": -372.78000000001117, "steps": 1764, "solved": false, "synops": 0, "wall_time_s": 0.019760608673095703, "config": {"num_train": 100, "num_test": 50, "max_steps": 1764, "reward_shaping": true, "visit_penalty": true, "wall_bump_cost": -0.3, "hazard_cost": -1.0, "goal_reward": 10.0, "code_hash": "fe0b8142940e55de"}, "lib_version": "v2"}, {"agent_name": "NoBackRandom", "maze_size": 21, "seed": 9216, "phase": "train", "episode": 20, "reward": -472.38000000001443, "steps": 1764, "solved": false, "synops": 0, "wall_time_s": 0.022019624710083008, "config": {"num_train": 100, "num_test": 50, "max_steps": 1764, "reward_shaping": true, "visit_penalty": true, "wall_bump_cost": -0.3, "hazard_cost": -1.0, "goal_reward": 10.0, "code_hash": "fe0b8142940e55de"}, "lib_version": "v2"}, {"agent_name": "NoBackRandom", "maze_size": 21, "seed": 9216, "phase": "train", "episode": 21, "reward": -394.6200000000127, "steps": 1764, "solved": false, "synops": 0, "wall_time_s": 0.017284631729125977, "config": {"num_train": 100, "num_test": 50, "max_steps": 1764, "reward_shaping": true, "visit_penalty": true, "wall_bump_cost": -0.3, "hazard_cost": -1.0, "goal_reward": 10.0, "code_hash": "fe0b8142940e55de"}, "lib_version": "v2"}, {"agent_name": "NoBackRandom", "maze_size": 21, "seed": 9216, "phase": "train", "episode": 22, "reward": -373.34000000001095, "steps": 1764, "solved": false, "synops": 0, "wall_time_s": 0.024653196334838867, "config": {"num_train": 100, "num_test": 50, "max_steps": 1764, "reward_shaping": true, "visit_penalty": true, "wall_bump_cost": -0.3, "hazard_cost": -1.0, "goal_reward": 10.0, "code_hash": "fe0b8142940e55de"}, "lib_version": "v2"}, {"agent_name": "NoBackRandom", "maze_size": 21, "seed": 9216, "phase": "train", "episode": 23, "reward": -379.2200000000102, "steps": 1764, "solved": false, "synops": 0, "wall_time_s": 0.02053070068359375, "config": {"num_train": 100, "num_test": 50, "max_steps": 1764, "reward_shaping": true, "visit_penalty": true, "wall_bump_cost": -0.3, "hazard_cost": -1.0, "goal_reward": 10.0, "code_hash": "fe0b8142940e55de"}, "lib_version": "v2"}, {"agent_name": "NoBackRandom", "maze_size": 21, "seed": 9216, "phase": "train", "episode": 24, "reward": -426.16000000001094, "steps": 1764, "solved": false, "synops": 0, "wall_time_s": 0.021081209182739258, "config": {"num_train": 100, "num_test": 50, "max_steps": 1764, "reward_shaping": true, "visit_penalty": true, "wall_bump_cost": -0.3, "hazard_cost": -1.0, "goal_reward": 10.0, "code_hash": "fe0b8142940e55de"}, "lib_version": "v2"}, {"agent_name": "NoBackRandom", "maze_size": 21, "seed": 9216, "phase": "train", "episode": 25, "reward": -413.30000000001326, "steps": 1764, "solved": false, "synops": 0, "wall_time_s": 0.022777080535888672, "config": {"num_train": 100, "num_test": 50, "max_steps": 1764, "reward_shaping": true, "visit_penalty": true, "wall_bump_cost": -0.3, "hazard_cost": -1.0, "goal_reward": 10.0, "code_hash": "fe0b8142940e55de"}, "lib_version": "v2"}, {"agent_name": "NoBackRandom", "maze_size": 21, "seed": 9216, "phase": "train", "episode": 26, "reward": -371.56000000000995, "steps": 1764, "solved": false, "synops": 0, "wall_time_s": 0.024890422821044922, "config": {"num_train": 100, "num_test": 50, "max_steps": 1764, "reward_shaping": true, "visit_penalty": true, "wall_bump_cost": -0.3, "hazard_cost": -1.0, "goal_reward": 10.0, "code_hash": "fe0b8142940e55de"}, "lib_version": "v2"}, {"agent_name": "NoBackRandom", "maze_size": 21, "seed": 9216, "phase": "train", "episode": 27, "reward": -381.6400000000113, "steps": 1764, "solved": false, "synops": 0, "wall_time_s": 0.02493119239807129, "config": {"num_train": 100, "num_test": 50, "max_steps": 1764, "reward_shaping": true, "visit_penalty": true, "wall_bump_cost": -0.3, "hazard_cost": -1.0, "goal_reward": 10.0, "code_hash": "fe0b8142940e55de"}, "lib_version": "v2"}, {"agent_name": "NoBackRandom", "maze_size": 21, "seed": 9216, "phase": "train", "episode": 28, "reward": -387.86000000001127, "steps": 1764, "solved": false, "synops": 0, "wall_time_s": 0.018132686614990234, "config": {"num_train": 100, "num_test": 50, "max_steps": 1764, "reward_shaping": true, "visit_penalty": true, "wall_bump_cost": -0.3, "hazard_cost": -1.0, "goal_reward": 10.0, "code_hash": "fe0b8142940e55de"}, "lib_version": "v2"}, {"agent_name": "NoBackRandom", "maze_size": 21, "seed": 9216, "phase": "train", "episode": 29, "reward": -398.9200000000113, "steps": 1764, "solved": false, "synops": 0, "wall_time_s": 0.02154088020324707, "config": {"num_train": 100, "num_test": 50, "max_steps": 1764, "reward_shaping": true, "visit_penalty": true, "wall_bump_cost": -0.3, "hazard_cost": -1.0, "goal_reward": 10.0, "code_hash": "fe0b8142940e55de"}, "lib_version": "v2"}, {"agent_name": "NoBackRandom", "maze_size": 21, "seed": 9216, "phase": "train", "episode": 30, "reward": -402.50000000001154, "steps": 1764, "solved": false, "synops": 0, "wall_time_s": 0.020535945892333984, "config": {"num_train": 100, "num_test": 50, "max_steps": 1764, "reward_shaping": true, "visit_penalty": true, "wall_bump_cost": -0.3, "hazard_cost": -1.0, "goal_reward": 10.0, "code_hash": "fe0b8142940e55de"}, "lib_version": "v2"}, {"agent_name": "NoBackRandom", "maze_size": 21, "seed": 9216, "phase": "train", "episode": 31, "reward": -425.4000000000123, "steps": 1764, "solved": false, "synops": 0, "wall_time_s": 0.02835369110107422, "config": {"num_train": 100, "num_test": 50, "max_steps": 1764, "reward_shaping": true, "visit_penalty": true, "wall_bump_cost": -0.3, "hazard_cost": -1.0, "goal_reward": 10.0, "code_hash": "fe0b8142940e55de"}, "lib_version": "v2"}, {"agent_name": "NoBackRandom", "maze_size": 21, "seed": 9216, "phase": "train", "episode": 32, "reward": -403.6200000000114, "steps": 1764, "solved": false, "synops": 0, "wall_time_s": 0.019081830978393555, "config": {"num_train": 100, "num_test": 50, "max_steps": 1764, "reward_shaping": true, "visit_penalty": true, "wall_bump_cost": -0.3, "hazard_cost": -1.0, "goal_reward": 10.0, "code_hash": "fe0b8142940e55de"}, "lib_version": "v2"}, {"agent_name": "NoBackRandom", "maze_size": 21, "seed": 9216, "phase": "train", "episode": 33, "reward": -380.7800000000112, "steps": 1764, "solved": false, "synops": 0, "wall_time_s": 0.017313480377197266, "config": {"num_train": 100, "num_test": 50, "max_steps": 1764, "reward_shaping": true, "visit_penalty": true, "wall_bump_cost": -0.3, "hazard_cost": -1.0, "goal_reward": 10.0, "code_hash": "fe0b8142940e55de"}, "lib_version": "v2"}, {"agent_name": "NoBackRandom", "maze_size": 21, "seed": 9216, "phase": "train", "episode": 34, "reward": -394.88000000001153, "steps": 1764, "solved": false, "synops": 0, "wall_time_s": 0.02260279655456543, "config": {"num_train": 100, "num_test": 50, "max_steps": 1764, "reward_shaping": true, "visit_penalty": true, "wall_bump_cost": -0.3, "hazard_cost": -1.0, "goal_reward": 10.0, "code_hash": "fe0b8142940e55de"}, "lib_version": "v2"}, {"agent_name": "NoBackRandom", "maze_size": 21, "seed": 9216, "phase": "train", "episode": 35, "reward": -396.6000000000113, "steps": 1764, "solved": false, "synops": 0, "wall_time_s": 0.015636205673217773, "config": {"num_train": 100, "num_test": 50, "max_steps": 1764, "reward_shaping": true, "visit_penalty": true, "wall_bump_cost": -0.3, "hazard_cost": -1.0, "goal_reward": 10.0, "code_hash": "fe0b8142940e55de"}, "lib_version": "v2"}, {"agent_name": "NoBackRandom", "maze_size": 21, "seed": 9216, "phase": "train", "episode": 36, "reward": -373.12000000001, "steps": 1764, "solved": false, "synops": 0, "wall_time_s": 0.020447969436645508, "config": {"num_train": 100, "num_test": 50, "max_steps": 1764, "reward_shaping": true, "visit_penalty": true, "wall_bump_cost": -0.3, "hazard_cost": -1.0, "goal_reward": 10.0, "code_hash": "fe0b8142940e55de"}, "lib_version": "v2"}, {"agent_name": "NoBackRandom", "maze_size": 21, "seed": 9216, "phase": "train", "episode": 37, "reward": -421.3800000000115, "steps": 1764, "solved": false, "synops": 0, "wall_time_s": 0.007955551147460938, "config": {"num_train": 100, "num_test": 50, "max_steps": 1764, "reward_shaping": true, "visit_penalty": true, "wall_bump_cost": -0.3, "hazard_cost": -1.0, "goal_reward": 10.0, "code_hash": "fe0b8142940e55de"}, "lib_version": "v2"}, {"agent_name": "NoBackRandom", "maze_size": 21, "seed": 9216, "phase": "train", "episode": 38, "reward": -378.06000000001035, "steps": 1764, "solved": false, "synops": 0, "wall_time_s": 0.035292863845825195, "config": {"num_train": 100, "num_test": 50, "max_steps": 1764, "reward_shaping": true, "visit_penalty": true, "wall_bump_cost": -0.3, "hazard_cost": -1.0, "goal_reward": 10.0, "code_hash": "fe0b8142940e55de"}, "lib_version": "v2"}, {"agent_name": "NoBackRandom", "maze_size": 21, "seed": 9216, "phase": "train", "episode": 39, "reward": -402.54000000001207, "steps": 1764, "solved": false, "synops": 0, "wall_time_s": 0.022353410720825195, "config": {"num_train": 100, "num_test": 50, "max_steps": 1764, "reward_shaping": true, "visit_penalty": true, "wall_bump_cost": -0.3, "hazard_cost": -1.0, "goal_reward": 10.0, "code_hash": "fe0b8142940e55de"}, "lib_version": "v2"}, {"agent_name": "NoBackRandom", "maze_size": 21, "seed": 9216, "phase": "train", "episode": 40, "reward": -382.700000000011, "steps": 1764, "solved": false, "synops": 0, "wall_time_s": 0.020531654357910156, "config": {"num_train": 100, "num_test": 50, "max_steps": 1764, "reward_shaping": true, "visit_penalty": true, "wall_bump_cost": -0.3, "hazard_cost": -1.0, "goal_reward": 10.0, "code_hash": "fe0b8142940e55de"}, "lib_version": "v2"}, {"agent_name": "NoBackRandom", "maze_size": 21, "seed": 9216, "phase": "train", "episode": 41, "reward": -173.06000000000023, "steps": 785, "solved": true, "synops": 0, "wall_time_s": 0.009631156921386719, "config": {"num_train": 100, "num_test": 50, "max_steps": 1764, "reward_shaping": true, "visit_penalty": true, "wall_bump_cost": -0.3, "hazard_cost": -1.0, "goal_reward": 10.0, "code_hash": "fe0b8142940e55de"}, "lib_version": "v2"}, {"agent_name": "NoBackRandom", "maze_size": 21, "seed": 9216, "phase": "train", "episode": 42, "reward": -407.140000000013, "steps": 1764, "solved": false, "synops": 0, "wall_time_s": 0.02207803726196289, "config": {"num_train": 100, "num_test": 50, "max_steps": 1764, "reward_shaping": true, "visit_penalty": true, "wall_bump_cost": -0.3, "hazard_cost": -1.0, "goal_reward": 10.0, "code_hash": "fe0b8142940e55de"}, "lib_version": "v2"}, {"agent_name": "NoBackRandom", "maze_size": 21, "seed": 9216, "phase": "train", "episode": 43, "reward": -383.56000000001126, "steps": 1764, "solved": false, "synops": 0, "wall_time_s": 0.02374434471130371, "config": {"num_train": 100, "num_test": 50, "max_steps": 1764, "reward_shaping": true, "visit_penalty": true, "wall_bump_cost": -0.3, "hazard_cost": -1.0, "goal_reward": 10.0, "code_hash": "fe0b8142940e55de"}, "lib_version": "v2"}, {"agent_name": "NoBackRandom", "maze_size": 21, "seed": 9216, "phase": "train", "episode": 44, "reward": -377.7400000000108, "steps": 1764, "solved": false, "synops": 0, "wall_time_s": 0.01878190040588379, "config": {"num_train": 100, "num_test": 50, "max_steps": 1764, "reward_shaping": true, "visit_penalty": true, "wall_bump_cost": -0.3, "hazard_cost": -1.0, "goal_reward": 10.0, "code_hash": "fe0b8142940e55de"}, "lib_version": "v2"}, {"agent_name": "NoBackRandom", "maze_size": 21, "seed": 9216, "phase": "train", "episode": 45, "reward": -110.05999999999932, "steps": 596, "solved": true, "synops": 0, "wall_time_s": 0.005589962005615234, "config": {"num_train": 100, "num_test": 50, "max_steps": 1764, "reward_shaping": true, "visit_penalty": true, "wall_bump_cost": -0.3, "hazard_cost": -1.0, "goal_reward": 10.0, "code_hash": "fe0b8142940e55de"}, "lib_version": "v2"}, {"agent_name": "NoBackRandom", "maze_size": 21, "seed": 9216, "phase": "train", "episode": 46, "reward": -384.6200000000113, "steps": 1764, "solved": false, "synops": 0, "wall_time_s": 0.014061212539672852, "config": {"num_train": 100, "num_test": 50, "max_steps": 1764, "reward_shaping": true, "visit_penalty": true, "wall_bump_cost": -0.3, "hazard_cost": -1.0, "goal_reward": 10.0, "code_hash": "fe0b8142940e55de"}, "lib_version": "v2"}, {"agent_name": "NoBackRandom", "maze_size": 21, "seed": 9216, "phase": "train", "episode": 47, "reward": -397.00000000001086, "steps": 1764, "solved": false, "synops": 0, "wall_time_s": 0.030337810516357422, "config": {"num_train": 100, "num_test": 50, "max_steps": 1764, "reward_shaping": true, "visit_penalty": true, "wall_bump_cost": -0.3, "hazard_cost": -1.0, "goal_reward": 10.0, "code_hash": "fe0b8142940e55de"}, "lib_version": "v2"}, {"agent_name": "NoBackRandom", "maze_size": 21, "seed": 9216, "phase": "train", "episode": 48, "reward": -381.0400000000107, "steps": 1764, "solved": false, "synops": 0, "wall_time_s": 0.017684221267700195, "config": {"num_train": 100, "num_test": 50, "max_steps": 1764, "reward_shaping": true, "visit_penalty": true, "wall_bump_cost": -0.3, "hazard_cost": -1.0, "goal_reward": 10.0, "code_hash": "fe0b8142940e55de"}, "lib_version": "v2"}, {"agent_name": "NoBackRandom", "maze_size": 21, "seed": 9216, "phase": "train", "episode": 49, "reward": -377.86000000001076, "steps": 1764, "solved": false, "synops": 0, "wall_time_s": 0.025079727172851562, "config": {"num_train": 100, "num_test": 50, "max_steps": 1764, "reward_shaping": true, "visit_penalty": true, "wall_bump_cost": -0.3, "hazard_cost": -1.0, "goal_reward": 10.0, "code_hash": "fe0b8142940e55de"}, "lib_version": "v2"}, {"agent_name": "NoBackRandom", "maze_size": 21, "seed": 9216, "phase": "train", "episode": 50, "reward": -395.76000000001164, "steps": 1764, "solved": false, "synops": 0, "wall_time_s": 0.02081751823425293, "config": {"num_train": 100, "num_test": 50, "max_steps": 1764, "reward_shaping": true, "visit_penalty": true, "wall_bump_cost": -0.3, "hazard_cost": -1.0, "goal_reward": 10.0, "code_hash": "fe0b8142940e55de"}, "lib_version": "v2"}, {"agent_name": "NoBackRandom", "maze_size": 21, "seed": 9216, "phase": "train", "episode": 51, "reward": -420.22000000001196, "steps": 1764, "solved": false, "synops": 0, "wall_time_s": 0.017971038818359375, "config": {"num_train": 100, "num_test": 50, "max_steps": 1764, "reward_shaping": true, "visit_penalty": true, "wall_bump_cost": -0.3, "hazard_cost": -1.0, "goal_reward": 10.0, "code_hash": "fe0b8142940e55de"}, "lib_version": "v2"}, {"agent_name": "NoBackRandom", "maze_size": 21, "seed": 9216, "phase": "train", "episode": 52, "reward": -375.9800000000112, "steps": 1764, "solved": false, "synops": 0, "wall_time_s": 0.023433446884155273, "config": {"num_train": 100, "num_test": 50, "max_steps": 1764, "reward_shaping": true, "visit_penalty": true, "wall_bump_cost": -0.3, "hazard_cost": -1.0, "goal_reward": 10.0, "code_hash": "fe0b8142940e55de"}, "lib_version": "v2"}, {"agent_name": "NoBackRandom", "maze_size": 21, "seed": 9216, "phase": "train", "episode": 53, "reward": -385.86000000001206, "steps": 1764, "solved": false, "synops": 0, "wall_time_s": 0.02980494499206543, "config": {"num_train": 100, "num_test": 50, "max_steps": 1764, "reward_shaping": true, "visit_penalty": true, "wall_bump_cost": -0.3, "hazard_cost": -1.0, "goal_reward": 10.0, "code_hash": "fe0b8142940e55de"}, "lib_version": "v2"}, {"agent_name": "NoBackRandom", "maze_size": 21, "seed": 9216, "phase": "train", "episode": 54, "reward": -366.14000000001056, "steps": 1764, "solved": false, "synops": 0, "wall_time_s": 0.01761484146118164, "config": {"num_train": 100, "num_test": 50, "max_steps": 1764, "reward_shaping": true, "visit_penalty": true, "wall_bump_cost": -0.3, "hazard_cost": -1.0, "goal_reward": 10.0, "code_hash": "fe0b8142940e55de"}, "lib_version": "v2"}, {"agent_name": "NoBackRandom", "maze_size": 21, "seed": 9216, "phase": "train", "episode": 55, "reward": -379.84000000001066, "steps": 1764, "solved": false, "synops": 0, "wall_time_s": 0.021672964096069336, "config": {"num_train": 100, "num_test": 50, "max_steps": 1764, "reward_shaping": true, "visit_penalty": true, "wall_bump_cost": -0.3, "hazard_cost": -1.0, "goal_reward": 10.0, "code_hash": "fe0b8142940e55de"}, "lib_version": "v2"}, {"agent_name": "NoBackRandom", "maze_size": 21, "seed": 9216, "phase": "train", "episode": 56, "reward": -405.34000000001146, "steps": 1764, "solved": false, "synops": 0, "wall_time_s": 0.02344226837158203, "config": {"num_train": 100, "num_test": 50, "max_steps": 1764, "reward_shaping": true, "visit_penalty": true, "wall_bump_cost": -0.3, "hazard_cost": -1.0, "goal_reward": 10.0, "code_hash": "fe0b8142940e55de"}, "lib_version": "v2"}, {"agent_name": "NoBackRandom", "maze_size": 21, "seed": 9216, "phase": "train", "episode": 57, "reward": -387.6800000000115, "steps": 1764, "solved": false, "synops": 0, "wall_time_s": 0.020701169967651367, "config": {"num_train": 100, "num_test": 50, "max_steps": 1764, "reward_shaping": true, "visit_penalty": true, "wall_bump_cost": -0.3, "hazard_cost": -1.0, "goal_reward": 10.0, "code_hash": "fe0b8142940e55de"}, "lib_version": "v2"}, {"agent_name": "NoBackRandom", "maze_size": 21, "seed": 9216, "phase": "train", "episode": 58, "reward": -144.91999999999976, "steps": 717, "solved": true, "synops": 0, "wall_time_s": 0.006433725357055664, "config": {"num_train": 100, "num_test": 50, "max_steps": 1764, "reward_shaping": true, "visit_penalty": true, "wall_bump_cost": -0.3, "hazard_cost": -1.0, "goal_reward": 10.0, "code_hash": "fe0b8142940e55de"}, "lib_version": "v2"}, {"agent_name": "NoBackRandom", "maze_size": 21, "seed": 9216, "phase": "train", "episode": 59, "reward": -386.68000000001166, "steps": 1764, "solved": false, "synops": 0, "wall_time_s": 0.02319812774658203, "config": {"num_train": 100, "num_test": 50, "max_steps": 1764, "reward_shaping": true, "visit_penalty": true, "wall_bump_cost": -0.3, "hazard_cost": -1.0, "goal_reward": 10.0, "code_hash": "fe0b8142940e55de"}, "lib_version": "v2"}, {"agent_name": "NoBackRandom", "maze_size": 21, "seed": 9216, "phase": "train", "episode": 60, "reward": -394.3600000000118, "steps": 1764, "solved": false, "synops": 0, "wall_time_s": 0.023920297622680664, "config": {"num_train": 100, "num_test": 50, "max_steps": 1764, "reward_shaping": true, "visit_penalty": true, "wall_bump_cost": -0.3, "hazard_cost": -1.0, "goal_reward": 10.0, "code_hash": "fe0b8142940e55de"}, "lib_version": "v2"}, {"agent_name": "NoBackRandom", "maze_size": 21, "seed": 9216, "phase": "train", "episode": 61, "reward": -399.8600000000109, "steps": 1764, "solved": false, "synops": 0, "wall_time_s": 0.020663738250732422, "config": {"num_train": 100, "num_test": 50, "max_steps": 1764, "reward_shaping": true, "visit_penalty": true, "wall_bump_cost": -0.3, "hazard_cost": -1.0, "goal_reward": 10.0, "code_hash": "fe0b8142940e55de"}, "lib_version": "v2"}, {"agent_name": "NoBackRandom", "maze_size": 21, "seed": 9216, "phase": "train", "episode": 62, "reward": -378.6200000000111, "steps": 1764, "solved": false, "synops": 0, "wall_time_s": 0.021241426467895508, "config": {"num_train": 100, "num_test": 50, "max_steps": 1764, "reward_shaping": true, "visit_penalty": true, "wall_bump_cost": -0.3, "hazard_cost": -1.0, "goal_reward": 10.0, "code_hash": "fe0b8142940e55de"}, "lib_version": "v2"}, {"agent_name": "NoBackRandom", "maze_size": 21, "seed": 9216, "phase": "train", "episode": 63, "reward": -374.02000000001055, "steps": 1764, "solved": false, "synops": 0, "wall_time_s": 0.022350311279296875, "config": {"num_train": 100, "num_test": 50, "max_steps": 1764, "reward_shaping": true, "visit_penalty": true, "wall_bump_cost": -0.3, "hazard_cost": -1.0, "goal_reward": 10.0, "code_hash": "fe0b8142940e55de"}, "lib_version": "v2"}, {"agent_name": "NoBackRandom", "maze_size": 21, "seed": 9216, "phase": "train", "episode": 64, "reward": -389.0000000000121, "steps": 1764, "solved": false, "synops": 0, "wall_time_s": 0.014644622802734375, "config": {"num_train": 100, "num_test": 50, "max_steps": 1764, "reward_shaping": true, "visit_penalty": true, "wall_bump_cost": -0.3, "hazard_cost": -1.0, "goal_reward": 10.0, "code_hash": "fe0b8142940e55de"}, "lib_version": "v2"}, {"agent_name": "NoBackRandom", "maze_size": 21, "seed": 9216, "phase": "train", "episode": 65, "reward": -399.6800000000112, "steps": 1764, "solved": false, "synops": 0, "wall_time_s": 0.033908843994140625, "config": {"num_train": 100, "num_test": 50, "max_steps": 1764, "reward_shaping": true, "visit_penalty": true, "wall_bump_cost": -0.3, "hazard_cost": -1.0, "goal_reward": 10.0, "code_hash": "fe0b8142940e55de"}, "lib_version": "v2"}, {"agent_name": "NoBackRandom", "maze_size": 21, "seed": 9216, "phase": "train", "episode": 66, "reward": -385.9400000000111, "steps": 1764, "solved": false, "synops": 0, "wall_time_s": 0.021062612533569336, "config": {"num_train": 100, "num_test": 50, "max_steps": 1764, "reward_shaping": true, "visit_penalty": true, "wall_bump_cost": -0.3, "hazard_cost": -1.0, "goal_reward": 10.0, "code_hash": "fe0b8142940e55de"}, "lib_version": "v2"}, {"agent_name": "NoBackRandom", "maze_size": 21, "seed": 9216, "phase": "train", "episode": 67, "reward": -429.6800000000124, "steps": 1764, "solved": false, "synops": 0, "wall_time_s": 0.02333521842956543, "config": {"num_train": 100, "num_test": 50, "max_steps": 1764, "reward_shaping": true, "visit_penalty": true, "wall_bump_cost": -0.3, "hazard_cost": -1.0, "goal_reward": 10.0, "code_hash": "fe0b8142940e55de"}, "lib_version": "v2"}, {"agent_name": "NoBackRandom", "maze_size": 21, "seed": 9216, "phase": "train", "episode": 68, "reward": -404.6000000000126, "steps": 1764, "solved": false, "synops": 0, "wall_time_s": 0.03177142143249512, "config": {"num_train": 100, "num_test": 50, "max_steps": 1764, "reward_shaping": true, "visit_penalty": true, "wall_bump_cost": -0.3, "hazard_cost": -1.0, "goal_reward": 10.0, "code_hash": "fe0b8142940e55de"}, "lib_version": "v2"}, {"agent_name": "NoBackRandom", "maze_size": 21, "seed": 9216, "phase": "train", "episode": 69, "reward": -412.9200000000141, "steps": 1764, "solved": false, "synops": 0, "wall_time_s": 0.030196666717529297, "config": {"num_train": 100, "num_test": 50, "max_steps": 1764, "reward_shaping": true, "visit_penalty": true, "wall_bump_cost": -0.3, "hazard_cost": -1.0, "goal_reward": 10.0, "code_hash": "fe0b8142940e55de"}, "lib_version": "v2"}, {"agent_name": "NoBackRandom", "maze_size": 21, "seed": 9216, "phase": "train", "episode": 70, "reward": -412.34000000001254, "steps": 1764, "solved": false, "synops": 0, "wall_time_s": 0.02711653709411621, "config": {"num_train": 100, "num_test": 50, "max_steps": 1764, "reward_shaping": true, "visit_penalty": true, "wall_bump_cost": -0.3, "hazard_cost": -1.0, "goal_reward": 10.0, "code_hash": "fe0b8142940e55de"}, "lib_version": "v2"}, {"agent_name": "NoBackRandom", "maze_size": 21, "seed": 9216, "phase": "train", "episode": 71, "reward": -394.0800000000121, "steps": 1764, "solved": false, "synops": 0, "wall_time_s": 0.016658306121826172, "config": {"num_train": 100, "num_test": 50, "max_steps": 1764, "reward_shaping": true, "visit_penalty": true, "wall_bump_cost": -0.3, "hazard_cost": -1.0, "goal_reward": 10.0, "code_hash": "fe0b8142940e55de"}, "lib_version": "v2"}, {"agent_name": "NoBackRandom", "maze_size": 21, "seed": 9216, "phase": "train", "episode": 72, "reward": -409.9400000000114, "steps": 1764, "solved": false, "synops": 0, "wall_time_s": 0.024548053741455078, "config": {"num_train": 100, "num_test": 50, "max_steps": 1764, "reward_shaping": true, "visit_penalty": true, "wall_bump_cost": -0.3, "hazard_cost": -1.0, "goal_reward": 10.0, "code_hash": "fe0b8142940e55de"}, "lib_version": "v2"}, {"agent_name": "NoBackRandom", "maze_size": 21, "seed": 9216, "phase": "train", "episode": 73, "reward": -429.4400000000126, "steps": 1764, "solved": false, "synops": 0, "wall_time_s": 0.022821426391601562, "config": {"num_train": 100, "num_test": 50, "max_steps": 1764, "reward_shaping": true, "visit_penalty": true, "wall_bump_cost": -0.3, "hazard_cost": -1.0, "goal_reward": 10.0, "code_hash": "fe0b8142940e55de"}, "lib_version": "v2"}, {"agent_name": "NoBackRandom", "maze_size": 21, "seed": 9216, "phase": "train", "episode": 74, "reward": -413.10000000001384, "steps": 1764, "solved": false, "synops": 0, "wall_time_s": 0.023311376571655273, "config": {"num_train": 100, "num_test": 50, "max_steps": 1764, "reward_shaping": true, "visit_penalty": true, "wall_bump_cost": -0.3, "hazard_cost": -1.0, "goal_reward": 10.0, "code_hash": "fe0b8142940e55de"}, "lib_version": "v2"}, {"agent_name": "NoBackRandom", "maze_size": 21, "seed": 9216, "phase": "train", "episode": 75, "reward": -399.0400000000121, "steps": 1764, "solved": false, "synops": 0, "wall_time_s": 0.01999378204345703, "config": {"num_train": 100, "num_test": 50, "max_steps": 1764, "reward_shaping": true, "visit_penalty": true, "wall_bump_cost": -0.3, "hazard_cost": -1.0, "goal_reward": 10.0, "code_hash": "fe0b8142940e55de"}, "lib_version": "v2"}, {"agent_name": "NoBackRandom", "maze_size": 21, "seed": 9216, "phase": "train", "episode": 76, "reward": -376.5000000000111, "steps": 1764, "solved": false, "synops": 0, "wall_time_s": 0.023757219314575195, "config": {"num_train": 100, "num_test": 50, "max_steps": 1764, "reward_shaping": true, "visit_penalty": true, "wall_bump_cost": -0.3, "hazard_cost": -1.0, "goal_reward": 10.0, "code_hash": "fe0b8142940e55de"}, "lib_version": "v2"}, {"agent_name": "NoBackRandom", "maze_size": 21, "seed": 9216, "phase": "train", "episode": 77, "reward": -222.58000000000152, "steps": 1092, "solved": true, "synops": 0, "wall_time_s": 0.014396429061889648, "config": {"num_train": 100, "num_test": 50, "max_steps": 1764, "reward_shaping": true, "visit_penalty": true, "wall_bump_cost": -0.3, "hazard_cost": -1.0, "goal_reward": 10.0, "code_hash": "fe0b8142940e55de"}, "lib_version": "v2"}, {"agent_name": "NoBackRandom", "maze_size": 21, "seed": 9216, "phase": "train", "episode": 78, "reward": -384.0000000000111, "steps": 1764, "solved": false, "synops": 0, "wall_time_s": 0.02464151382446289, "config": {"num_train": 100, "num_test": 50, "max_steps": 1764, "reward_shaping": true, "visit_penalty": true, "wall_bump_cost": -0.3, "hazard_cost": -1.0, "goal_reward": 10.0, "code_hash": "fe0b8142940e55de"}, "lib_version": "v2"}, {"agent_name": "NoBackRandom", "maze_size": 21, "seed": 9216, "phase": "train", "episode": 79, "reward": -370.6600000000103, "steps": 1764, "solved": false, "synops": 0, "wall_time_s": 0.016408205032348633, "config": {"num_train": 100, "num_test": 50, "max_steps": 1764, "reward_shaping": true, "visit_penalty": true, "wall_bump_cost": -0.3, "hazard_cost": -1.0, "goal_reward": 10.0, "code_hash": "fe0b8142940e55de"}, "lib_version": "v2"}, {"agent_name": "NoBackRandom", "maze_size": 21, "seed": 9216, "phase": "train", "episode": 80, "reward": -381.20000000001147, "steps": 1764, "solved": false, "synops": 0, "wall_time_s": 0.027134180068969727, "config": {"num_train": 100, "num_test": 50, "max_steps": 1764, "reward_shaping": true, "visit_penalty": true, "wall_bump_cost": -0.3, "hazard_cost": -1.0, "goal_reward": 10.0, "code_hash": "fe0b8142940e55de"}, "lib_version": "v2"}, {"agent_name": "NoBackRandom", "maze_size": 21, "seed": 9216, "phase": "train", "episode": 81, "reward": -379.4400000000114, "steps": 1764, "solved": false, "synops": 0, "wall_time_s": 0.022495031356811523, "config": {"num_train": 100, "num_test": 50, "max_steps": 1764, "reward_shaping": true, "visit_penalty": true, "wall_bump_cost": -0.3, "hazard_cost": -1.0, "goal_reward": 10.0, "code_hash": "fe0b8142940e55de"}, "lib_version": "v2"}, {"agent_name": "NoBackRandom", "maze_size": 21, "seed": 9216, "phase": "train", "episode": 82, "reward": -394.1000000000114, "steps": 1764, "solved": false, "synops": 0, "wall_time_s": 0.016694068908691406, "config": {"num_train": 100, "num_test": 50, "max_steps": 1764, "reward_shaping": true, "visit_penalty": true, "wall_bump_cost": -0.3, "hazard_cost": -1.0, "goal_reward": 10.0, "code_hash": "fe0b8142940e55de"}, "lib_version": "v2"}, {"agent_name": "NoBackRandom", "maze_size": 21, "seed": 9216, "phase": "train", "episode": 83, "reward": -385.6800000000091, "steps": 1764, "solved": false, "synops": 0, "wall_time_s": 0.022440195083618164, "config": {"num_train": 100, "num_test": 50, "max_steps": 1764, "reward_shaping": true, "visit_penalty": true, "wall_bump_cost": -0.3, "hazard_cost": -1.0, "goal_reward": 10.0, "code_hash": "fe0b8142940e55de"}, "lib_version": "v2"}, {"agent_name": "NoBackRandom", "maze_size": 21, "seed": 9216, "phase": "train", "episode": 84, "reward": -364.9800000000104, "steps": 1764, "solved": false, "synops": 0, "wall_time_s": 0.020161151885986328, "config": {"num_train": 100, "num_test": 50, "max_steps": 1764, "reward_shaping": true, "visit_penalty": true, "wall_bump_cost": -0.3, "hazard_cost": -1.0, "goal_reward": 10.0, "code_hash": "fe0b8142940e55de"}, "lib_version": "v2"}, {"agent_name": "NoBackRandom", "maze_size": 21, "seed": 9216, "phase": "train", "episode": 85, "reward": -399.20000000001215, "steps": 1764, "solved": false, "synops": 0, "wall_time_s": 0.02579951286315918, "config": {"num_train": 100, "num_test": 50, "max_steps": 1764, "reward_shaping": true, "visit_penalty": true, "wall_bump_cost": -0.3, "hazard_cost": -1.0, "goal_reward": 10.0, "code_hash": "fe0b8142940e55de"}, "lib_version": "v2"}, {"agent_name": "NoBackRandom", "maze_size": 21, "seed": 9216, "phase": "train", "episode": 86, "reward": -388.26000000001056, "steps": 1764, "solved": false, "synops": 0, "wall_time_s": 0.027439594268798828, "config": {"num_train": 100, "num_test": 50, "max_steps": 1764, "reward_shaping": true, "visit_penalty": true, "wall_bump_cost": -0.3, "hazard_cost": -1.0, "goal_reward": 10.0, "code_hash": "fe0b8142940e55de"}, "lib_version": "v2"}, {"agent_name": "NoBackRandom", "maze_size": 21, "seed": 9216, "phase": "train", "episode": 87, "reward": -369.52000000001055, "steps": 1764, "solved": false, "synops": 0, "wall_time_s": 0.02832198143005371, "config": {"num_train": 100, "num_test": 50, "max_steps": 1764, "reward_shaping": true, "visit_penalty": true, "wall_bump_cost": -0.3, "hazard_cost": -1.0, "goal_reward": 10.0, "code_hash": "fe0b8142940e55de"}, "lib_version": "v2"}, {"agent_name": "NoBackRandom", "maze_size": 21, "seed": 9216, "phase": "train", "episode": 88, "reward": -440.04000000001326, "steps": 1764, "solved": false, "synops": 0, "wall_time_s": 0.021565914154052734, "config": {"num_train": 100, "num_test": 50, "max_steps": 1764, "reward_shaping": true, "visit_penalty": true, "wall_bump_cost": -0.3, "hazard_cost": -1.0, "goal_reward": 10.0, "code_hash": "fe0b8142940e55de"}, "lib_version": "v2"}, {"agent_name": "NoBackRandom", "maze_size": 21, "seed": 9216, "phase": "train", "episode": 89, "reward": -412.1200000000116, "steps": 1764, "solved": false, "synops": 0, "wall_time_s": 0.025162696838378906, "config": {"num_train": 100, "num_test": 50, "max_steps": 1764, "reward_shaping": true, "visit_penalty": true, "wall_bump_cost": -0.3, "hazard_cost": -1.0, "goal_reward": 10.0, "code_hash": "fe0b8142940e55de"}, "lib_version": "v2"}, {"agent_name": "NoBackRandom", "maze_size": 21, "seed": 9216, "phase": "train", "episode": 90, "reward": -384.7200000000103, "steps": 1764, "solved": false, "synops": 0, "wall_time_s": 0.018099308013916016, "config": {"num_train": 100, "num_test": 50, "max_steps": 1764, "reward_shaping": true, "visit_penalty": true, "wall_bump_cost": -0.3, "hazard_cost": -1.0, "goal_reward": 10.0, "code_hash": "fe0b8142940e55de"}, "lib_version": "v2"}, {"agent_name": "NoBackRandom", "maze_size": 21, "seed": 9216, "phase": "train", "episode": 91, "reward": -374.6400000000109, "steps": 1764, "solved": false, "synops": 0, "wall_time_s": 0.028198719024658203, "config": {"num_train": 100, "num_test": 50, "max_steps": 1764, "reward_shaping": true, "visit_penalty": true, "wall_bump_cost": -0.3, "hazard_cost": -1.0, "goal_reward": 10.0, "code_hash": "fe0b8142940e55de"}, "lib_version": "v2"}, {"agent_name": "NoBackRandom", "maze_size": 21, "seed": 9216, "phase": "train", "episode": 92, "reward": -138.4399999999996, "steps": 714, "solved": true, "synops": 0, "wall_time_s": 0.007909536361694336, "config": {"num_train": 100, "num_test": 50, "max_steps": 1764, "reward_shaping": true, "visit_penalty": true, "wall_bump_cost": -0.3, "hazard_cost": -1.0, "goal_reward": 10.0, "code_hash": "fe0b8142940e55de"}, "lib_version": "v2"}, {"agent_name": "NoBackRandom", "maze_size": 21, "seed": 9216, "phase": "train", "episode": 93, "reward": -401.160000000012, "steps": 1764, "solved": false, "synops": 0, "wall_time_s": 0.020425796508789062, "config": {"num_train": 100, "num_test": 50, "max_steps": 1764, "reward_shaping": true, "visit_penalty": true, "wall_bump_cost": -0.3, "hazard_cost": -1.0, "goal_reward": 10.0, "code_hash": "fe0b8142940e55de"}, "lib_version": "v2"}, {"agent_name": "NoBackRandom", "maze_size": 21, "seed": 9216, "phase": "train", "episode": 94, "reward": -366.9600000000109, "steps": 1764, "solved": false, "synops": 0, "wall_time_s": 0.018280506134033203, "config": {"num_train": 100, "num_test": 50, "max_steps": 1764, "reward_shaping": true, "visit_penalty": true, "wall_bump_cost": -0.3, "hazard_cost": -1.0, "goal_reward": 10.0, "code_hash": "fe0b8142940e55de"}, "lib_version": "v2"}, {"agent_name": "NoBackRandom", "maze_size": 21, "seed": 9216, "phase": "train", "episode": 95, "reward": -383.28000000001197, "steps": 1764, "solved": false, "synops": 0, "wall_time_s": 0.017205476760864258, "config": {"num_train": 100, "num_test": 50, "max_steps": 1764, "reward_shaping": true, "visit_penalty": true, "wall_bump_cost": -0.3, "hazard_cost": -1.0, "goal_reward": 10.0, "code_hash": "fe0b8142940e55de"}, "lib_version": "v2"}, {"agent_name": "NoBackRandom", "maze_size": 21, "seed": 9216, "phase": "train", "episode": 96, "reward": -411.600000000012, "steps": 1764, "solved": false, "synops": 0, "wall_time_s": 0.02007770538330078, "config": {"num_train": 100, "num_test": 50, "max_steps": 1764, "reward_shaping": true, "visit_penalty": true, "wall_bump_cost": -0.3, "hazard_cost": -1.0, "goal_reward": 10.0, "code_hash": "fe0b8142940e55de"}, "lib_version": "v2"}, {"agent_name": "NoBackRandom", "maze_size": 21, "seed": 9216, "phase": "train", "episode": 97, "reward": -380.14000000001136, "steps": 1764, "solved": false, "synops": 0, "wall_time_s": 0.0173492431640625, "config": {"num_train": 100, "num_test": 50, "max_steps": 1764, "reward_shaping": true, "visit_penalty": true, "wall_bump_cost": -0.3, "hazard_cost": -1.0, "goal_reward": 10.0, "code_hash": "fe0b8142940e55de"}, "lib_version": "v2"}, {"agent_name": "NoBackRandom", "maze_size": 21, "seed": 9216, "phase": "train", "episode": 98, "reward": -406.84000000001083, "steps": 1764, "solved": false, "synops": 0, "wall_time_s": 0.019176006317138672, "config": {"num_train": 100, "num_test": 50, "max_steps": 1764, "reward_shaping": true, "visit_penalty": true, "wall_bump_cost": -0.3, "hazard_cost": -1.0, "goal_reward": 10.0, "code_hash": "fe0b8142940e55de"}, "lib_version": "v2"}, {"agent_name": "NoBackRandom", "maze_size": 21, "seed": 9216, "phase": "train", "episode": 99, "reward": -432.34000000001214, "steps": 1764, "solved": false, "synops": 0, "wall_time_s": 0.026787996292114258, "config": {"num_train": 100, "num_test": 50, "max_steps": 1764, "reward_shaping": true, "visit_penalty": true, "wall_bump_cost": -0.3, "hazard_cost": -1.0, "goal_reward": 10.0, "code_hash": "fe0b8142940e55de"}, "lib_version": "v2"}, {"agent_name": "NoBackRandom", "maze_size": 21, "seed": 9216, "phase": "test", "episode": 0, "reward": -381.840000000011, "steps": 1764, "solved": false, "synops": 0, "wall_time_s": 0.018928050994873047, "config": {"num_train": 100, "num_test": 50, "max_steps": 1764, "reward_shaping": true, "visit_penalty": true, "wall_bump_cost": -0.3, "hazard_cost": -1.0, "goal_reward": 10.0, "code_hash": "fe0b8142940e55de"}, "lib_version": "v2"}, {"agent_name": "NoBackRandom", "maze_size": 21, "seed": 9216, "phase": "test", "episode": 1, "reward": -372.86000000001076, "steps": 1764, "solved": false, "synops": 0, "wall_time_s": 0.018405914306640625, "config": {"num_train": 100, "num_test": 50, "max_steps": 1764, "reward_shaping": true, "visit_penalty": true, "wall_bump_cost": -0.3, "hazard_cost": -1.0, "goal_reward": 10.0, "code_hash": "fe0b8142940e55de"}, "lib_version": "v2"}, {"agent_name": "NoBackRandom", "maze_size": 21, "seed": 9216, "phase": "test", "episode": 2, "reward": -376.04000000001105, "steps": 1764, "solved": false, "synops": 0, "wall_time_s": 0.0211789608001709, "config": {"num_train": 100, "num_test": 50, "max_steps": 1764, "reward_shaping": true, "visit_penalty": true, "wall_bump_cost": -0.3, "hazard_cost": -1.0, "goal_reward": 10.0, "code_hash": "fe0b8142940e55de"}, "lib_version": "v2"}, {"agent_name": "NoBackRandom", "maze_size": 21, "seed": 9216, "phase": "test", "episode": 3, "reward": -398.5200000000113, "steps": 1764, "solved": false, "synops": 0, "wall_time_s": 0.022713184356689453, "config": {"num_train": 100, "num_test": 50, "max_steps": 1764, "reward_shaping": true, "visit_penalty": true, "wall_bump_cost": -0.3, "hazard_cost": -1.0, "goal_reward": 10.0, "code_hash": "fe0b8142940e55de"}, "lib_version": "v2"}, {"agent_name": "NoBackRandom", "maze_size": 21, "seed": 9216, "phase": "test", "episode": 4, "reward": -372.48000000001053, "steps": 1764, "solved": false, "synops": 0, "wall_time_s": 0.016277074813842773, "config": {"num_train": 100, "num_test": 50, "max_steps": 1764, "reward_shaping": true, "visit_penalty": true, "wall_bump_cost": -0.3, "hazard_cost": -1.0, "goal_reward": 10.0, "code_hash": "fe0b8142940e55de"}, "lib_version": "v2"}, {"agent_name": "NoBackRandom", "maze_size": 21, "seed": 9216, "phase": "test", "episode": 5, "reward": -386.5200000000115, "steps": 1764, "solved": false, "synops": 0, "wall_time_s": 0.024974822998046875, "config": {"num_train": 100, "num_test": 50, "max_steps": 1764, "reward_shaping": true, "visit_penalty": true, "wall_bump_cost": -0.3, "hazard_cost": -1.0, "goal_reward": 10.0, "code_hash": "fe0b8142940e55de"}, "lib_version": "v2"}, {"agent_name": "NoBackRandom", "maze_size": 21, "seed": 9216, "phase": "test", "episode": 6, "reward": -437.0200000000136, "steps": 1764, "solved": false, "synops": 0, "wall_time_s": 0.02720952033996582, "config": {"num_train": 100, "num_test": 50, "max_steps": 1764, "reward_shaping": true, "visit_penalty": true, "wall_bump_cost": -0.3, "hazard_cost": -1.0, "goal_reward": 10.0, "code_hash": "fe0b8142940e55de"}, "lib_version": "v2"}, {"agent_name": "NoBackRandom", "maze_size": 21, "seed": 9216, "phase": "test", "episode": 7, "reward": -424.2800000000122, "steps": 1764, "solved": false, "synops": 0, "wall_time_s": 0.018415212631225586, "config": {"num_train": 100, "num_test": 50, "max_steps": 1764, "reward_shaping": true, "visit_penalty": true, "wall_bump_cost": -0.3, "hazard_cost": -1.0, "goal_reward": 10.0, "code_hash": "fe0b8142940e55de"}, "lib_version": "v2"}, {"agent_name": "NoBackRandom", "maze_size": 21, "seed": 9216, "phase": "test", "episode": 8, "reward": -388.32000000001125, "steps": 1764, "solved": false, "synops": 0, "wall_time_s": 0.027462244033813477, "config": {"num_train": 100, "num_test": 50, "max_steps": 1764, "reward_shaping": true, "visit_penalty": true, "wall_bump_cost": -0.3, "hazard_cost": -1.0, "goal_reward": 10.0, "code_hash": "fe0b8142940e55de"}, "lib_version": "v2"}, {"agent_name": "NoBackRandom", "maze_size": 21, "seed": 9216, "phase": "test", "episode": 9, "reward": -278.4600000000043, "steps": 1320, "solved": true, "synops": 0, "wall_time_s": 0.018700122833251953, "config": {"num_train": 100, "num_test": 50, "max_steps": 1764, "reward_shaping": true, "visit_penalty": true, "wall_bump_cost": -0.3, "hazard_cost": -1.0, "goal_reward": 10.0, "code_hash": "fe0b8142940e55de"}, "lib_version": "v2"}, {"agent_name": "NoBackRandom", "maze_size": 21, "seed": 9216, "phase": "test", "episode": 10, "reward": -419.6400000000118, "steps": 1764, "solved": false, "synops": 0, "wall_time_s": 0.02441859245300293, "config": {"num_train": 100, "num_test": 50, "max_steps": 1764, "reward_shaping": true, "visit_penalty": true, "wall_bump_cost": -0.3, "hazard_cost": -1.0, "goal_reward": 10.0, "code_hash": "fe0b8142940e55de"}, "lib_version": "v2"}, {"agent_name": "NoBackRandom", "maze_size": 21, "seed": 9216, "phase": "test", "episode": 11, "reward": -388.66000000001185, "steps": 1764, "solved": false, "synops": 0, "wall_time_s": 0.020270824432373047, "config": {"num_train": 100, "num_test": 50, "max_steps": 1764, "reward_shaping": true, "visit_penalty": true, "wall_bump_cost": -0.3, "hazard_cost": -1.0, "goal_reward": 10.0, "code_hash": "fe0b8142940e55de"}, "lib_version": "v2"}, {"agent_name": "NoBackRandom", "maze_size": 21, "seed": 9216, "phase": "test", "episode": 12, "reward": -374.00000000001063, "steps": 1764, "solved": false, "synops": 0, "wall_time_s": 0.013306617736816406, "config": {"num_train": 100, "num_test": 50, "max_steps": 1764, "reward_shaping": true, "visit_penalty": true, "wall_bump_cost": -0.3, "hazard_cost": -1.0, "goal_reward": 10.0, "code_hash": "fe0b8142940e55de"}, "lib_version": "v2"}, {"agent_name": "NoBackRandom", "maze_size": 21, "seed": 9216, "phase": "test", "episode": 13, "reward": -375.9600000000104, "steps": 1764, "solved": false, "synops": 0, "wall_time_s": 0.026155710220336914, "config": {"num_train": 100, "num_test": 50, "max_steps": 1764, "reward_shaping": true, "visit_penalty": true, "wall_bump_cost": -0.3, "hazard_cost": -1.0, "goal_reward": 10.0, "code_hash": "fe0b8142940e55de"}, "lib_version": "v2"}, {"agent_name": "NoBackRandom", "maze_size": 21, "seed": 9216, "phase": "test", "episode": 14, "reward": -392.8200000000116, "steps": 1764, "solved": false, "synops": 0, "wall_time_s": 0.016722440719604492, "config": {"num_train": 100, "num_test": 50, "max_steps": 1764, "reward_shaping": true, "visit_penalty": true, "wall_bump_cost": -0.3, "hazard_cost": -1.0, "goal_reward": 10.0, "code_hash": "fe0b8142940e55de"}, "lib_version": "v2"}, {"agent_name": "NoBackRandom", "maze_size": 21, "seed": 9216, "phase": "test", "episode": 15, "reward": -388.60000000001145, "steps": 1764, "solved": false, "synops": 0, "wall_time_s": 0.01677417755126953, "config": {"num_train": 100, "num_test": 50, "max_steps": 1764, "reward_shaping": true, "visit_penalty": true, "wall_bump_cost": -0.3, "hazard_cost": -1.0, "goal_reward": 10.0, "code_hash": "fe0b8142940e55de"}, "lib_version": "v2"}, {"agent_name": "NoBackRandom", "maze_size": 21, "seed": 9216, "phase": "test", "episode": 16, "reward": -413.000000000012, "steps": 1764, "solved": false, "synops": 0, "wall_time_s": 0.02006077766418457, "config": {"num_train": 100, "num_test": 50, "max_steps": 1764, "reward_shaping": true, "visit_penalty": true, "wall_bump_cost": -0.3, "hazard_cost": -1.0, "goal_reward": 10.0, "code_hash": "fe0b8142940e55de"}, "lib_version": "v2"}, {"agent_name": "NoBackRandom", "maze_size": 21, "seed": 9216, "phase": "test", "episode": 17, "reward": -431.82000000001193, "steps": 1764, "solved": false, "synops": 0, "wall_time_s": 0.016701936721801758, "config": {"num_train": 100, "num_test": 50, "max_steps": 1764, "reward_shaping": true, "visit_penalty": true, "wall_bump_cost": -0.3, "hazard_cost": -1.0, "goal_reward": 10.0, "code_hash": "fe0b8142940e55de"}, "lib_version": "v2"}, {"agent_name": "NoBackRandom", "maze_size": 21, "seed": 9216, "phase": "test", "episode": 18, "reward": -357.9400000000104, "steps": 1764, "solved": false, "synops": 0, "wall_time_s": 0.023867368698120117, "config": {"num_train": 100, "num_test": 50, "max_steps": 1764, "reward_shaping": true, "visit_penalty": true, "wall_bump_cost": -0.3, "hazard_cost": -1.0, "goal_reward": 10.0, "code_hash": "fe0b8142940e55de"}, "lib_version": "v2"}, {"agent_name": "NoBackRandom", "maze_size": 21, "seed": 9216, "phase": "test", "episode": 19, "reward": -396.84000000001254, "steps": 1764, "solved": false, "synops": 0, "wall_time_s": 0.021636009216308594, "config": {"num_train": 100, "num_test": 50, "max_steps": 1764, "reward_shaping": true, "visit_penalty": true, "wall_bump_cost": -0.3, "hazard_cost": -1.0, "goal_reward": 10.0, "code_hash": "fe0b8142940e55de"}, "lib_version": "v2"}, {"agent_name": "NoBackRandom", "maze_size": 21, "seed": 9216, "phase": "test", "episode": 20, "reward": -387.9000000000104, "steps": 1764, "solved": false, "synops": 0, "wall_time_s": 0.015025854110717773, "config": {"num_train": 100, "num_test": 50, "max_steps": 1764, "reward_shaping": true, "visit_penalty": true, "wall_bump_cost": -0.3, "hazard_cost": -1.0, "goal_reward": 10.0, "code_hash": "fe0b8142940e55de"}, "lib_version": "v2"}, {"agent_name": "NoBackRandom", "maze_size": 21, "seed": 9216, "phase": "test", "episode": 21, "reward": -402.02000000001334, "steps": 1764, "solved": false, "synops": 0, "wall_time_s": 0.02124476432800293, "config": {"num_train": 100, "num_test": 50, "max_steps": 1764, "reward_shaping": true, "visit_penalty": true, "wall_bump_cost": -0.3, "hazard_cost": -1.0, "goal_reward": 10.0, "code_hash": "fe0b8142940e55de"}, "lib_version": "v2"}, {"agent_name": "NoBackRandom", "maze_size": 21, "seed": 9216, "phase": "test", "episode": 22, "reward": -395.6000000000118, "steps": 1764, "solved": false, "synops": 0, "wall_time_s": 0.02397298812866211, "config": {"num_train": 100, "num_test": 50, "max_steps": 1764, "reward_shaping": true, "visit_penalty": true, "wall_bump_cost": -0.3, "hazard_cost": -1.0, "goal_reward": 10.0, "code_hash": "fe0b8142940e55de"}, "lib_version": "v2"}, {"agent_name": "NoBackRandom", "maze_size": 21, "seed": 9216, "phase": "test", "episode": 23, "reward": -381.74000000001075, "steps": 1764, "solved": false, "synops": 0, "wall_time_s": 0.016769886016845703, "config": {"num_train": 100, "num_test": 50, "max_steps": 1764, "reward_shaping": true, "visit_penalty": true, "wall_bump_cost": -0.3, "hazard_cost": -1.0, "goal_reward": 10.0, "code_hash": "fe0b8142940e55de"}, "lib_version": "v2"}, {"agent_name": "NoBackRandom", "maze_size": 21, "seed": 9216, "phase": "test", "episode": 24, "reward": -405.0400000000117, "steps": 1764, "solved": false, "synops": 0, "wall_time_s": 0.01525425910949707, "config": {"num_train": 100, "num_test": 50, "max_steps": 1764, "reward_shaping": true, "visit_penalty": true, "wall_bump_cost": -0.3, "hazard_cost": -1.0, "goal_reward": 10.0, "code_hash": "fe0b8142940e55de"}, "lib_version": "v2"}, {"agent_name": "NoBackRandom", "maze_size": 21, "seed": 9216, "phase": "test", "episode": 25, "reward": -377.3200000000115, "steps": 1764, "solved": false, "synops": 0, "wall_time_s": 0.022503376007080078, "config": {"num_train": 100, "num_test": 50, "max_steps": 1764, "reward_shaping": true, "visit_penalty": true, "wall_bump_cost": -0.3, "hazard_cost": -1.0, "goal_reward": 10.0, "code_hash": "fe0b8142940e55de"}, "lib_version": "v2"}, {"agent_name": "NoBackRandom", "maze_size": 21, "seed": 9216, "phase": "test", "episode": 26, "reward": -378.80000000000973, "steps": 1764, "solved": false, "synops": 0, "wall_time_s": 0.020815372467041016, "config": {"num_train": 100, "num_test": 50, "max_steps": 1764, "reward_shaping": true, "visit_penalty": true, "wall_bump_cost": -0.3, "hazard_cost": -1.0, "goal_reward": 10.0, "code_hash": "fe0b8142940e55de"}, "lib_version": "v2"}, {"agent_name": "NoBackRandom", "maze_size": 21, "seed": 9216, "phase": "test", "episode": 27, "reward": -380.20000000001085, "steps": 1764, "solved": false, "synops": 0, "wall_time_s": 0.016597509384155273, "config": {"num_train": 100, "num_test": 50, "max_steps": 1764, "reward_shaping": true, "visit_penalty": true, "wall_bump_cost": -0.3, "hazard_cost": -1.0, "goal_reward": 10.0, "code_hash": "fe0b8142940e55de"}, "lib_version": "v2"}, {"agent_name": "NoBackRandom", "maze_size": 21, "seed": 9216, "phase": "test", "episode": 28, "reward": -382.42000000001036, "steps": 1764, "solved": false, "synops": 0, "wall_time_s": 0.015465974807739258, "config": {"num_train": 100, "num_test": 50, "max_steps": 1764, "reward_shaping": true, "visit_penalty": true, "wall_bump_cost": -0.3, "hazard_cost": -1.0, "goal_reward": 10.0, "code_hash": "fe0b8142940e55de"}, "lib_version": "v2"}, {"agent_name": "NoBackRandom", "maze_size": 21, "seed": 9216, "phase": "test", "episode": 29, "reward": -92.59999999999965, "steps": 490, "solved": true, "synops": 0, "wall_time_s": 0.0, "config": {"num_train": 100, "num_test": 50, "max_steps": 1764, "reward_shaping": true, "visit_penalty": true, "wall_bump_cost": -0.3, "hazard_cost": -1.0, "goal_reward": 10.0, "code_hash": "fe0b8142940e55de"}, "lib_version": "v2"}, {"agent_name": "NoBackRandom", "maze_size": 21, "seed": 9216, "phase": "test", "episode": 30, "reward": -408.64000000001255, "steps": 1764, "solved": false, "synops": 0, "wall_time_s": 0.02442145347595215, "config": {"num_train": 100, "num_test": 50, "max_steps": 1764, "reward_shaping": true, "visit_penalty": true, "wall_bump_cost": -0.3, "hazard_cost": -1.0, "goal_reward": 10.0, "code_hash": "fe0b8142940e55de"}, "lib_version": "v2"}, {"agent_name": "NoBackRandom", "maze_size": 21, "seed": 9216, "phase": "test", "episode": 31, "reward": -377.7200000000099, "steps": 1764, "solved": false, "synops": 0, "wall_time_s": 0.022877216339111328, "config": {"num_train": 100, "num_test": 50, "max_steps": 1764, "reward_shaping": true, "visit_penalty": true, "wall_bump_cost": -0.3, "hazard_cost": -1.0, "goal_reward": 10.0, "code_hash": "fe0b8142940e55de"}, "lib_version": "v2"}, {"agent_name": "NoBackRandom", "maze_size": 21, "seed": 9216, "phase": "test", "episode": 32, "reward": -398.88000000001244, "steps": 1764, "solved": false, "synops": 0, "wall_time_s": 0.0222322940826416, "config": {"num_train": 100, "num_test": 50, "max_steps": 1764, "reward_shaping": true, "visit_penalty": true, "wall_bump_cost": -0.3, "hazard_cost": -1.0, "goal_reward": 10.0, "code_hash": "fe0b8142940e55de"}, "lib_version": "v2"}, {"agent_name": "NoBackRandom", "maze_size": 21, "seed": 9216, "phase": "test", "episode": 33, "reward": -380.3600000000109, "steps": 1764, "solved": false, "synops": 0, "wall_time_s": 0.013068199157714844, "config": {"num_train": 100, "num_test": 50, "max_steps": 1764, "reward_shaping": true, "visit_penalty": true, "wall_bump_cost": -0.3, "hazard_cost": -1.0, "goal_reward": 10.0, "code_hash": "fe0b8142940e55de"}, "lib_version": "v2"}, {"agent_name": "NoBackRandom", "maze_size": 21, "seed": 9216, "phase": "test", "episode": 34, "reward": -375.56000000001154, "steps": 1764, "solved": false, "synops": 0, "wall_time_s": 0.017470598220825195, "config": {"num_train": 100, "num_test": 50, "max_steps": 1764, "reward_shaping": true, "visit_penalty": true, "wall_bump_cost": -0.3, "hazard_cost": -1.0, "goal_reward": 10.0, "code_hash": "fe0b8142940e55de"}, "lib_version": "v2"}, {"agent_name": "NoBackRandom", "maze_size": 21, "seed": 9216, "phase": "test", "episode": 35, "reward": -449.56000000001285, "steps": 1764, "solved": false, "synops": 0, "wall_time_s": 0.016890764236450195, "config": {"num_train": 100, "num_test": 50, "max_steps": 1764, "reward_shaping": true, "visit_penalty": true, "wall_bump_cost": -0.3, "hazard_cost": -1.0, "goal_reward": 10.0, "code_hash": "fe0b8142940e55de"}, "lib_version": "v2"}, {"agent_name": "NoBackRandom", "maze_size": 21, "seed": 9216, "phase": "test", "episode": 36, "reward": -394.860000000011, "steps": 1764, "solved": false, "synops": 0, "wall_time_s": 0.017754077911376953, "config": {"num_train": 100, "num_test": 50, "max_steps": 1764, "reward_shaping": true, "visit_penalty": true, "wall_bump_cost": -0.3, "hazard_cost": -1.0, "goal_reward": 10.0, "code_hash": "fe0b8142940e55de"}, "lib_version": "v2"}, {"agent_name": "NoBackRandom", "maze_size": 21, "seed": 9216, "phase": "test", "episode": 37, "reward": -196.060000000001, "steps": 814, "solved": true, "synops": 0, "wall_time_s": 0.0035016536712646484, "config": {"num_train": 100, "num_test": 50, "max_steps": 1764, "reward_shaping": true, "visit_penalty": true, "wall_bump_cost": -0.3, "hazard_cost": -1.0, "goal_reward": 10.0, "code_hash": "fe0b8142940e55de"}, "lib_version": "v2"}, {"agent_name": "NoBackRandom", "maze_size": 21, "seed": 9216, "phase": "test", "episode": 38, "reward": -477.3200000000136, "steps": 1764, "solved": false, "synops": 0, "wall_time_s": 0.021327972412109375, "config": {"num_train": 100, "num_test": 50, "max_steps": 1764, "reward_shaping": true, "visit_penalty": true, "wall_bump_cost": -0.3, "hazard_cost": -1.0, "goal_reward": 10.0, "code_hash": "fe0b8142940e55de"}, "lib_version": "v2"}, {"agent_name": "NoBackRandom", "maze_size": 21, "seed": 9216, "phase": "test", "episode": 39, "reward": -400.940000000011, "steps": 1764, "solved": false, "synops": 0, "wall_time_s": 0.01708078384399414, "config": {"num_train": 100, "num_test": 50, "max_steps": 1764, "reward_shaping": true, "visit_penalty": true, "wall_bump_cost": -0.3, "hazard_cost": -1.0, "goal_reward": 10.0, "code_hash": "fe0b8142940e55de"}, "lib_version": "v2"}, {"agent_name": "NoBackRandom", "maze_size": 21, "seed": 9216, "phase": "test", "episode": 40, "reward": -394.2800000000108, "steps": 1764, "solved": false, "synops": 0, "wall_time_s": 0.017078161239624023, "config": {"num_train": 100, "num_test": 50, "max_steps": 1764, "reward_shaping": true, "visit_penalty": true, "wall_bump_cost": -0.3, "hazard_cost": -1.0, "goal_reward": 10.0, "code_hash": "fe0b8142940e55de"}, "lib_version": "v2"}, {"agent_name": "NoBackRandom", "maze_size": 21, "seed": 9216, "phase": "test", "episode": 41, "reward": -411.360000000012, "steps": 1764, "solved": false, "synops": 0, "wall_time_s": 0.0163114070892334, "config": {"num_train": 100, "num_test": 50, "max_steps": 1764, "reward_shaping": true, "visit_penalty": true, "wall_bump_cost": -0.3, "hazard_cost": -1.0, "goal_reward": 10.0, "code_hash": "fe0b8142940e55de"}, "lib_version": "v2"}, {"agent_name": "NoBackRandom", "maze_size": 21, "seed": 9216, "phase": "test", "episode": 42, "reward": -411.42000000001195, "steps": 1764, "solved": false, "synops": 0, "wall_time_s": 0.015221834182739258, "config": {"num_train": 100, "num_test": 50, "max_steps": 1764, "reward_shaping": true, "visit_penalty": true, "wall_bump_cost": -0.3, "hazard_cost": -1.0, "goal_reward": 10.0, "code_hash": "fe0b8142940e55de"}, "lib_version": "v2"}, {"agent_name": "NoBackRandom", "maze_size": 21, "seed": 9216, "phase": "test", "episode": 43, "reward": -437.1000000000127, "steps": 1764, "solved": false, "synops": 0, "wall_time_s": 0.02349400520324707, "config": {"num_train": 100, "num_test": 50, "max_steps": 1764, "reward_shaping": true, "visit_penalty": true, "wall_bump_cost": -0.3, "hazard_cost": -1.0, "goal_reward": 10.0, "code_hash": "fe0b8142940e55de"}, "lib_version": "v2"}, {"agent_name": "NoBackRandom", "maze_size": 21, "seed": 9216, "phase": "test", "episode": 44, "reward": -380.5600000000109, "steps": 1764, "solved": false, "synops": 0, "wall_time_s": 0.017105817794799805, "config": {"num_train": 100, "num_test": 50, "max_steps": 1764, "reward_shaping": true, "visit_penalty": true, "wall_bump_cost": -0.3, "hazard_cost": -1.0, "goal_reward": 10.0, "code_hash": "fe0b8142940e55de"}, "lib_version": "v2"}, {"agent_name": "NoBackRandom", "maze_size": 21, "seed": 9216, "phase": "test", "episode": 45, "reward": -405.720000000012, "steps": 1764, "solved": false, "synops": 0, "wall_time_s": 0.01789999008178711, "config": {"num_train": 100, "num_test": 50, "max_steps": 1764, "reward_shaping": true, "visit_penalty": true, "wall_bump_cost": -0.3, "hazard_cost": -1.0, "goal_reward": 10.0, "code_hash": "fe0b8142940e55de"}, "lib_version": "v2"}, {"agent_name": "NoBackRandom", "maze_size": 21, "seed": 9216, "phase": "test", "episode": 46, "reward": -402.90000000001214, "steps": 1764, "solved": false, "synops": 0, "wall_time_s": 0.019802093505859375, "config": {"num_train": 100, "num_test": 50, "max_steps": 1764, "reward_shaping": true, "visit_penalty": true, "wall_bump_cost": -0.3, "hazard_cost": -1.0, "goal_reward": 10.0, "code_hash": "fe0b8142940e55de"}, "lib_version": "v2"}, {"agent_name": "NoBackRandom", "maze_size": 21, "seed": 9216, "phase": "test", "episode": 47, "reward": -417.300000000012, "steps": 1764, "solved": false, "synops": 0, "wall_time_s": 0.014206886291503906, "config": {"num_train": 100, "num_test": 50, "max_steps": 1764, "reward_shaping": true, "visit_penalty": true, "wall_bump_cost": -0.3, "hazard_cost": -1.0, "goal_reward": 10.0, "code_hash": "fe0b8142940e55de"}, "lib_version": "v2"}, {"agent_name": "NoBackRandom", "maze_size": 21, "seed": 9216, "phase": "test", "episode": 48, "reward": -398.74000000001234, "steps": 1764, "solved": false, "synops": 0, "wall_time_s": 0.015250921249389648, "config": {"num_train": 100, "num_test": 50, "max_steps": 1764, "reward_shaping": true, "visit_penalty": true, "wall_bump_cost": -0.3, "hazard_cost": -1.0, "goal_reward": 10.0, "code_hash": "fe0b8142940e55de"}, "lib_version": "v2"}, {"agent_name": "NoBackRandom", "maze_size": 21, "seed": 9216, "phase": "test", "episode": 49, "reward": -431.22000000001304, "steps": 1764, "solved": false, "synops": 0, "wall_time_s": 0.02419567108154297, "config": {"num_train": 100, "num_test": 50, "max_steps": 1764, "reward_shaping": true, "visit_penalty": true, "wall_bump_cost": -0.3, "hazard_cost": -1.0, "goal_reward": 10.0, "code_hash": "fe0b8142940e55de"}, "lib_version": "v2"}]