[{"agent_name": "TabularQ_v2", "maze_size": 25, "seed": 42, "phase": "train", "episode": 0, "reward": -386.34000000001436, "steps": 2500, "solved": false, "synops": 0, "wall_time_s": 0.042200326919555664, "config": {"num_train": 100, "num_test": 50, "max_steps": 2500, "reward_shaping": true, "visit_penalty": true, "wall_bump_cost": -0.3, "hazard_cost": -1.0, "goal_reward": 10.0, "code_hash": "fe0b8142940e55de"}, "lib_version": "v2"}, {"agent_name": "TabularQ_v2", "maze_size": 25, "seed": 42, "phase": "train", "episode": 1, "reward": -45.4199999999997, "steps": 382, "solved": true, "synops": 0, "wall_time_s": 0.008764266967773438, "config": {"num_train": 100, "num_test": 50, "max_steps": 2500, "reward_shaping": true, "visit_penalty": true, "wall_bump_cost": -0.3, "hazard_cost": -1.0, "goal_reward": 10.0, "code_hash": "fe0b8142940e55de"}, "lib_version": "v2"}, {"agent_name": "TabularQ_v2", "maze_size": 25, "seed": 42, "phase": "train", "episode": 2, "reward": -389.6200000000164, "steps": 2500, "solved": false, "synops": 0, "wall_time_s": 0.0509181022644043, "config": {"num_train": 100, "num_test": 50, "max_steps": 2500, "reward_shaping": true, "visit_penalty": true, "wall_bump_cost": -0.3, "hazard_cost": -1.0, "goal_reward": 10.0, "code_hash": "fe0b8142940e55de"}, "lib_version": "v2"}, {"agent_name": "TabularQ_v2", "maze_size": 25, "seed": 42, "phase": "train", "episode": 3, "reward": -389.0400000000158, "steps": 2500, "solved": false, "synops": 0, "wall_time_s": 0.04925131797790527, "config": {"num_train": 100, "num_test": 50, "max_steps": 2500, "reward_shaping": true, "visit_penalty": true, "wall_bump_cost": -0.3, "hazard_cost": -1.0, "goal_reward": 10.0, "code_hash": "fe0b8142940e55de"}, "lib_version": "v2"}, {"agent_name": "TabularQ_v2", "maze_size": 25, "seed": 42, "phase": "train", "episode": 4, "reward": -204.21999999999974, "steps": 1235, "solved": true, "synops": 0, "wall_time_s": 0.025464534759521484, "config": {"num_train": 100, "num_test": 50, "max_steps": 2500, "reward_shaping": true, "visit_penalty": true, "wall_bump_cost": -0.3, "hazard_cost": -1.0, "goal_reward": 10.0, "code_hash": "fe0b8142940e55de"}, "lib_version": "v2"}, {"agent_name": "TabularQ_v2", "maze_size": 25, "seed": 42, "phase": "train", "episode": 5, "reward": -426.0800000000188, "steps": 2500, "solved": false, "synops": 0, "wall_time_s": 0.04094529151916504, "config": {"num_train": 100, "num_test": 50, "max_steps": 2500, "reward_shaping": true, "visit_penalty": true, "wall_bump_cost": -0.3, "hazard_cost": -1.0, "goal_reward": 10.0, "code_hash": "fe0b8142940e55de"}, "lib_version": "v2"}, {"agent_name": "TabularQ_v2", "maze_size": 25, "seed": 42, "phase": "train", "episode": 6, "reward": -413.94000000001705, "steps": 2500, "solved": false, "synops": 0, "wall_time_s": 0.048940420150756836, "config": {"num_train": 100, "num_test": 50, "max_steps": 2500, "reward_shaping": true, "visit_penalty": true, "wall_bump_cost": -0.3, "hazard_cost": -1.0, "goal_reward": 10.0, "code_hash": "fe0b8142940e55de"}, "lib_version": "v2"}, {"agent_name": "TabularQ_v2", "maze_size": 25, "seed": 42, "phase": "train", "episode": 7, "reward": -299.48000000000604, "steps": 1968, "solved": true, "synops": 0, "wall_time_s": 0.03490805625915527, "config": {"num_train": 100, "num_test": 50, "max_steps": 2500, "reward_shaping": true, "visit_penalty": true, "wall_bump_cost": -0.3, "hazard_cost": -1.0, "goal_reward": 10.0, "code_hash": "fe0b8142940e55de"}, "lib_version": "v2"}, {"agent_name": "TabularQ_v2", "maze_size": 25, "seed": 42, "phase": "train", "episode": 8, "reward": -245.31999999999897, "steps": 1685, "solved": true, "synops": 0, "wall_time_s": 0.033255815505981445, "config": {"num_train": 100, "num_test": 50, "max_steps": 2500, "reward_shaping": true, "visit_penalty": true, "wall_bump_cost": -0.3, "hazard_cost": -1.0, "goal_reward": 10.0, "code_hash": "fe0b8142940e55de"}, "lib_version": "v2"}, {"agent_name": "TabularQ_v2", "maze_size": 25, "seed": 42, "phase": "train", "episode": 9, "reward": -408.7600000000179, "steps": 2500, "solved": false, "synops": 0, "wall_time_s": 0.05065011978149414, "config": {"num_train": 100, "num_test": 50, "max_steps": 2500, "reward_shaping": true, "visit_penalty": true, "wall_bump_cost": -0.3, "hazard_cost": -1.0, "goal_reward": 10.0, "code_hash": "fe0b8142940e55de"}, "lib_version": "v2"}, {"agent_name": "TabularQ_v2", "maze_size": 25, "seed": 42, "phase": "train", "episode": 10, "reward": -47.139999999999745, "steps": 344, "solved": true, "synops": 0, "wall_time_s": 0.008544206619262695, "config": {"num_train": 100, "num_test": 50, "max_steps": 2500, "reward_shaping": true, "visit_penalty": true, "wall_bump_cost": -0.3, "hazard_cost": -1.0, "goal_reward": 10.0, "code_hash": "fe0b8142940e55de"}, "lib_version": "v2"}, {"agent_name": "TabularQ_v2", "maze_size": 25, "seed": 42, "phase": "train", "episode": 11, "reward": -394.4800000000144, "steps": 2500, "solved": false, "synops": 0, "wall_time_s": 0.047197580337524414, "config": {"num_train": 100, "num_test": 50, "max_steps": 2500, "reward_shaping": true, "visit_penalty": true, "wall_bump_cost": -0.3, "hazard_cost": -1.0, "goal_reward": 10.0, "code_hash": "fe0b8142940e55de"}, "lib_version": "v2"}, {"agent_name": "TabularQ_v2", "maze_size": 25, "seed": 42, "phase": "train", "episode": 12, "reward": -423.56000000001603, "steps": 2500, "solved": false, "synops": 0, "wall_time_s": 0.04416632652282715, "config": {"num_train": 100, "num_test": 50, "max_steps": 2500, "reward_shaping": true, "visit_penalty": true, "wall_bump_cost": -0.3, "hazard_cost": -1.0, "goal_reward": 10.0, "code_hash": "fe0b8142940e55de"}, "lib_version": "v2"}, {"agent_name": "TabularQ_v2", "maze_size": 25, "seed": 42, "phase": "train", "episode": 13, "reward": -391.2200000000153, "steps": 2500, "solved": false, "synops": 0, "wall_time_s": 0.04216146469116211, "config": {"num_train": 100, "num_test": 50, "max_steps": 2500, "reward_shaping": true, "visit_penalty": true, "wall_bump_cost": -0.3, "hazard_cost": -1.0, "goal_reward": 10.0, "code_hash": "fe0b8142940e55de"}, "lib_version": "v2"}, {"agent_name": "TabularQ_v2", "maze_size": 25, "seed": 42, "phase": "train", "episode": 14, "reward": -386.5000000000152, "steps": 2500, "solved": false, "synops": 0, "wall_time_s": 0.05025506019592285, "config": {"num_train": 100, "num_test": 50, "max_steps": 2500, "reward_shaping": true, "visit_penalty": true, "wall_bump_cost": -0.3, "hazard_cost": -1.0, "goal_reward": 10.0, "code_hash": "fe0b8142940e55de"}, "lib_version": "v2"}, {"agent_name": "TabularQ_v2", "maze_size": 25, "seed": 42, "phase": "train", "episode": 15, "reward": -422.3000000000186, "steps": 2500, "solved": false, "synops": 0, "wall_time_s": 0.04227089881896973, "config": {"num_train": 100, "num_test": 50, "max_steps": 2500, "reward_shaping": true, "visit_penalty": true, "wall_bump_cost": -0.3, "hazard_cost": -1.0, "goal_reward": 10.0, "code_hash": "fe0b8142940e55de"}, "lib_version": "v2"}, {"agent_name": "TabularQ_v2", "maze_size": 25, "seed": 42, "phase": "train", "episode": 16, "reward": -68.95999999999944, "steps": 451, "solved": true, "synops": 0, "wall_time_s": 0.007880449295043945, "config": {"num_train": 100, "num_test": 50, "max_steps": 2500, "reward_shaping": true, "visit_penalty": true, "wall_bump_cost": -0.3, "hazard_cost": -1.0, "goal_reward": 10.0, "code_hash": "fe0b8142940e55de"}, "lib_version": "v2"}, {"agent_name": "TabularQ_v2", "maze_size": 25, "seed": 42, "phase": "train", "episode": 17, "reward": -396.3000000000151, "steps": 2500, "solved": false, "synops": 0, "wall_time_s": 0.04249882698059082, "config": {"num_train": 100, "num_test": 50, "max_steps": 2500, "reward_shaping": true, "visit_penalty": true, "wall_bump_cost": -0.3, "hazard_cost": -1.0, "goal_reward": 10.0, "code_hash": "fe0b8142940e55de"}, "lib_version": "v2"}, {"agent_name": "TabularQ_v2", "maze_size": 25, "seed": 42, "phase": "train", "episode": 18, "reward": -239.3999999999993, "steps": 1502, "solved": true, "synops": 0, "wall_time_s": 0.024150609970092773, "config": {"num_train": 100, "num_test": 50, "max_steps": 2500, "reward_shaping": true, "visit_penalty": true, "wall_bump_cost": -0.3, "hazard_cost": -1.0, "goal_reward": 10.0, "code_hash": "fe0b8142940e55de"}, "lib_version": "v2"}, {"agent_name": "TabularQ_v2", "maze_size": 25, "seed": 42, "phase": "train", "episode": 19, "reward": -325.24000000000785, "steps": 2033, "solved": true, "synops": 0, "wall_time_s": 0.04058384895324707, "config": {"num_train": 100, "num_test": 50, "max_steps": 2500, "reward_shaping": true, "visit_penalty": true, "wall_bump_cost": -0.3, "hazard_cost": -1.0, "goal_reward": 10.0, "code_hash": "fe0b8142940e55de"}, "lib_version": "v2"}, {"agent_name": "TabularQ_v2", "maze_size": 25, "seed": 42, "phase": "train", "episode": 20, "reward": -295.9400000000057, "steps": 1949, "solved": true, "synops": 0, "wall_time_s": 0.034627437591552734, "config": {"num_train": 100, "num_test": 50, "max_steps": 2500, "reward_shaping": true, "visit_penalty": true, "wall_bump_cost": -0.3, "hazard_cost": -1.0, "goal_reward": 10.0, "code_hash": "fe0b8142940e55de"}, "lib_version": "v2"}, {"agent_name": "TabularQ_v2", "maze_size": 25, "seed": 42, "phase": "train", "episode": 21, "reward": -215.55999999999952, "steps": 1347, "solved": true, "synops": 0, "wall_time_s": 0.022629261016845703, "config": {"num_train": 100, "num_test": 50, "max_steps": 2500, "reward_shaping": true, "visit_penalty": true, "wall_bump_cost": -0.3, "hazard_cost": -1.0, "goal_reward": 10.0, "code_hash": "fe0b8142940e55de"}, "lib_version": "v2"}, {"agent_name": "TabularQ_v2", "maze_size": 25, "seed": 42, "phase": "train", "episode": 22, "reward": -105.39999999999951, "steps": 700, "solved": true, "synops": 0, "wall_time_s": 0.010845422744750977, "config": {"num_train": 100, "num_test": 50, "max_steps": 2500, "reward_shaping": true, "visit_penalty": true, "wall_bump_cost": -0.3, "hazard_cost": -1.0, "goal_reward": 10.0, "code_hash": "fe0b8142940e55de"}, "lib_version": "v2"}, {"agent_name": "TabularQ_v2", "maze_size": 25, "seed": 42, "phase": "train", "episode": 23, "reward": -428.84000000001834, "steps": 2500, "solved": false, "synops": 0, "wall_time_s": 0.04203224182128906, "config": {"num_train": 100, "num_test": 50, "max_steps": 2500, "reward_shaping": true, "visit_penalty": true, "wall_bump_cost": -0.3, "hazard_cost": -1.0, "goal_reward": 10.0, "code_hash": "fe0b8142940e55de"}, "lib_version": "v2"}, {"agent_name": "TabularQ_v2", "maze_size": 25, "seed": 42, "phase": "train", "episode": 24, "reward": -294.12000000000364, "steps": 1811, "solved": true, "synops": 0, "wall_time_s": 0.03323054313659668, "config": {"num_train": 100, "num_test": 50, "max_steps": 2500, "reward_shaping": true, "visit_penalty": true, "wall_bump_cost": -0.3, "hazard_cost": -1.0, "goal_reward": 10.0, "code_hash": "fe0b8142940e55de"}, "lib_version": "v2"}, {"agent_name": "TabularQ_v2", "maze_size": 25, "seed": 42, "phase": "train", "episode": 25, "reward": -318.74000000000774, "steps": 2137, "solved": true, "synops": 0, "wall_time_s": 0.03349161148071289, "config": {"num_train": 100, "num_test": 50, "max_steps": 2500, "reward_shaping": true, "visit_penalty": true, "wall_bump_cost": -0.3, "hazard_cost": -1.0, "goal_reward": 10.0, "code_hash": "fe0b8142940e55de"}, "lib_version": "v2"}, {"agent_name": "TabularQ_v2", "maze_size": 25, "seed": 42, "phase": "train", "episode": 26, "reward": -390.1800000000149, "steps": 2500, "solved": false, "synops": 0, "wall_time_s": 0.04945516586303711, "config": {"num_train": 100, "num_test": 50, "max_steps": 2500, "reward_shaping": true, "visit_penalty": true, "wall_bump_cost": -0.3, "hazard_cost": -1.0, "goal_reward": 10.0, "code_hash": "fe0b8142940e55de"}, "lib_version": "v2"}, {"agent_name": "TabularQ_v2", "maze_size": 25, "seed": 42, "phase": "train", "episode": 27, "reward": -378.2800000000154, "steps": 2500, "solved": false, "synops": 0, "wall_time_s": 0.0429072380065918, "config": {"num_train": 100, "num_test": 50, "max_steps": 2500, "reward_shaping": true, "visit_penalty": true, "wall_bump_cost": -0.3, "hazard_cost": -1.0, "goal_reward": 10.0, "code_hash": "fe0b8142940e55de"}, "lib_version": "v2"}, {"agent_name": "TabularQ_v2", "maze_size": 25, "seed": 42, "phase": "train", "episode": 28, "reward": -397.28000000001623, "steps": 2500, "solved": false, "synops": 0, "wall_time_s": 0.04177069664001465, "config": {"num_train": 100, "num_test": 50, "max_steps": 2500, "reward_shaping": true, "visit_penalty": true, "wall_bump_cost": -0.3, "hazard_cost": -1.0, "goal_reward": 10.0, "code_hash": "fe0b8142940e55de"}, "lib_version": "v2"}, {"agent_name": "TabularQ_v2", "maze_size": 25, "seed": 42, "phase": "train", "episode": 29, "reward": -35.39999999999987, "steps": 292, "solved": true, "synops": 0, "wall_time_s": 0.00753021240234375, "config": {"num_train": 100, "num_test": 50, "max_steps": 2500, "reward_shaping": true, "visit_penalty": true, "wall_bump_cost": -0.3, "hazard_cost": -1.0, "goal_reward": 10.0, "code_hash": "fe0b8142940e55de"}, "lib_version": "v2"}, {"agent_name": "TabularQ_v2", "maze_size": 25, "seed": 42, "phase": "train", "episode": 30, "reward": -87.6199999999995, "steps": 654, "solved": true, "synops": 0, "wall_time_s": 0.009201288223266602, "config": {"num_train": 100, "num_test": 50, "max_steps": 2500, "reward_shaping": true, "visit_penalty": true, "wall_bump_cost": -0.3, "hazard_cost": -1.0, "goal_reward": 10.0, "code_hash": "fe0b8142940e55de"}, "lib_version": "v2"}, {"agent_name": "TabularQ_v2", "maze_size": 25, "seed": 42, "phase": "train", "episode": 31, "reward": -39.99999999999975, "steps": 317, "solved": true, "synops": 0, "wall_time_s": 0.007459163665771484, "config": {"num_train": 100, "num_test": 50, "max_steps": 2500, "reward_shaping": true, "visit_penalty": true, "wall_bump_cost": -0.3, "hazard_cost": -1.0, "goal_reward": 10.0, "code_hash": "fe0b8142940e55de"}, "lib_version": "v2"}, {"agent_name": "TabularQ_v2", "maze_size": 25, "seed": 42, "phase": "train", "episode": 32, "reward": -343.4000000000104, "steps": 2207, "solved": true, "synops": 0, "wall_time_s": 0.034833669662475586, "config": {"num_train": 100, "num_test": 50, "max_steps": 2500, "reward_shaping": true, "visit_penalty": true, "wall_bump_cost": -0.3, "hazard_cost": -1.0, "goal_reward": 10.0, "code_hash": "fe0b8142940e55de"}, "lib_version": "v2"}, {"agent_name": "TabularQ_v2", "maze_size": 25, "seed": 42, "phase": "train", "episode": 33, "reward": -152.39999999999992, "steps": 975, "solved": true, "synops": 0, "wall_time_s": 0.016447067260742188, "config": {"num_train": 100, "num_test": 50, "max_steps": 2500, "reward_shaping": true, "visit_penalty": true, "wall_bump_cost": -0.3, "hazard_cost": -1.0, "goal_reward": 10.0, "code_hash": "fe0b8142940e55de"}, "lib_version": "v2"}, {"agent_name": "TabularQ_v2", "maze_size": 25, "seed": 42, "phase": "train", "episode": 34, "reward": -389.2000000000152, "steps": 2500, "solved": false, "synops": 0, "wall_time_s": 0.04187917709350586, "config": {"num_train": 100, "num_test": 50, "max_steps": 2500, "reward_shaping": true, "visit_penalty": true, "wall_bump_cost": -0.3, "hazard_cost": -1.0, "goal_reward": 10.0, "code_hash": "fe0b8142940e55de"}, "lib_version": "v2"}, {"agent_name": "TabularQ_v2", "maze_size": 25, "seed": 42, "phase": "train", "episode": 35, "reward": -11.380000000000017, "steps": 171, "solved": true, "synops": 0, "wall_time_s": 0.009320259094238281, "config": {"num_train": 100, "num_test": 50, "max_steps": 2500, "reward_shaping": true, "visit_penalty": true, "wall_bump_cost": -0.3, "hazard_cost": -1.0, "goal_reward": 10.0, "code_hash": "fe0b8142940e55de"}, "lib_version": "v2"}, {"agent_name": "TabularQ_v2", "maze_size": 25, "seed": 42, "phase": "train", "episode": 36, "reward": -394.160000000016, "steps": 2500, "solved": false, "synops": 0, "wall_time_s": 0.04044294357299805, "config": {"num_train": 100, "num_test": 50, "max_steps": 2500, "reward_shaping": true, "visit_penalty": true, "wall_bump_cost": -0.3, "hazard_cost": -1.0, "goal_reward": 10.0, "code_hash": "fe0b8142940e55de"}, "lib_version": "v2"}, {"agent_name": "TabularQ_v2", "maze_size": 25, "seed": 42, "phase": "train", "episode": 37, "reward": -44.779999999999696, "steps": 393, "solved": true, "synops": 0, "wall_time_s": 0.008415937423706055, "config": {"num_train": 100, "num_test": 50, "max_steps": 2500, "reward_shaping": true, "visit_penalty": true, "wall_bump_cost": -0.3, "hazard_cost": -1.0, "goal_reward": 10.0, "code_hash": "fe0b8142940e55de"}, "lib_version": "v2"}, {"agent_name": "TabularQ_v2", "maze_size": 25, "seed": 42, "phase": "train", "episode": 38, "reward": -54.07999999999966, "steps": 353, "solved": true, "synops": 0, "wall_time_s": 0.010316133499145508, "config": {"num_train": 100, "num_test": 50, "max_steps": 2500, "reward_shaping": true, "visit_penalty": true, "wall_bump_cost": -0.3, "hazard_cost": -1.0, "goal_reward": 10.0, "code_hash": "fe0b8142940e55de"}, "lib_version": "v2"}, {"agent_name": "TabularQ_v2", "maze_size": 25, "seed": 42, "phase": "train", "episode": 39, "reward": -403.5600000000155, "steps": 2500, "solved": false, "synops": 0, "wall_time_s": 0.04021048545837402, "config": {"num_train": 100, "num_test": 50, "max_steps": 2500, "reward_shaping": true, "visit_penalty": true, "wall_bump_cost": -0.3, "hazard_cost": -1.0, "goal_reward": 10.0, "code_hash": "fe0b8142940e55de"}, "lib_version": "v2"}, {"agent_name": "TabularQ_v2", "maze_size": 25, "seed": 42, "phase": "train", "episode": 40, "reward": -389.32000000001614, "steps": 2500, "solved": false, "synops": 0, "wall_time_s": 0.04149889945983887, "config": {"num_train": 100, "num_test": 50, "max_steps": 2500, "reward_shaping": true, "visit_penalty": true, "wall_bump_cost": -0.3, "hazard_cost": -1.0, "goal_reward": 10.0, "code_hash": "fe0b8142940e55de"}, "lib_version": "v2"}, {"agent_name": "TabularQ_v2", "maze_size": 25, "seed": 42, "phase": "train", "episode": 41, "reward": -411.4200000000178, "steps": 2500, "solved": false, "synops": 0, "wall_time_s": 0.04961585998535156, "config": {"num_train": 100, "num_test": 50, "max_steps": 2500, "reward_shaping": true, "visit_penalty": true, "wall_bump_cost": -0.3, "hazard_cost": -1.0, "goal_reward": 10.0, "code_hash": "fe0b8142940e55de"}, "lib_version": "v2"}, {"agent_name": "TabularQ_v2", "maze_size": 25, "seed": 42, "phase": "train", "episode": 42, "reward": -266.24000000000245, "steps": 1631, "solved": true, "synops": 0, "wall_time_s": 0.02595233917236328, "config": {"num_train": 100, "num_test": 50, "max_steps": 2500, "reward_shaping": true, "visit_penalty": true, "wall_bump_cost": -0.3, "hazard_cost": -1.0, "goal_reward": 10.0, "code_hash": "fe0b8142940e55de"}, "lib_version": "v2"}, {"agent_name": "TabularQ_v2", "maze_size": 25, "seed": 42, "phase": "train", "episode": 43, "reward": -384.9000000000152, "steps": 2500, "solved": false, "synops": 0, "wall_time_s": 0.04546475410461426, "config": {"num_train": 100, "num_test": 50, "max_steps": 2500, "reward_shaping": true, "visit_penalty": true, "wall_bump_cost": -0.3, "hazard_cost": -1.0, "goal_reward": 10.0, "code_hash": "fe0b8142940e55de"}, "lib_version": "v2"}, {"agent_name": "TabularQ_v2", "maze_size": 25, "seed": 42, "phase": "train", "episode": 44, "reward": -420.980000000017, "steps": 2500, "solved": false, "synops": 0, "wall_time_s": 0.04581189155578613, "config": {"num_train": 100, "num_test": 50, "max_steps": 2500, "reward_shaping": true, "visit_penalty": true, "wall_bump_cost": -0.3, "hazard_cost": -1.0, "goal_reward": 10.0, "code_hash": "fe0b8142940e55de"}, "lib_version": "v2"}, {"agent_name": "TabularQ_v2", "maze_size": 25, "seed": 42, "phase": "train", "episode": 45, "reward": -388.82000000001585, "steps": 2500, "solved": false, "synops": 0, "wall_time_s": 0.04440903663635254, "config": {"num_train": 100, "num_test": 50, "max_steps": 2500, "reward_shaping": true, "visit_penalty": true, "wall_bump_cost": -0.3, "hazard_cost": -1.0, "goal_reward": 10.0, "code_hash": "fe0b8142940e55de"}, "lib_version": "v2"}, {"agent_name": "TabularQ_v2", "maze_size": 25, "seed": 42, "phase": "train", "episode": 46, "reward": -253.91999999999933, "steps": 1632, "solved": true, "synops": 0, "wall_time_s": 0.032196998596191406, "config": {"num_train": 100, "num_test": 50, "max_steps": 2500, "reward_shaping": true, "visit_penalty": true, "wall_bump_cost": -0.3, "hazard_cost": -1.0, "goal_reward": 10.0, "code_hash": "fe0b8142940e55de"}, "lib_version": "v2"}, {"agent_name": "TabularQ_v2", "maze_size": 25, "seed": 42, "phase": "train", "episode": 47, "reward": -401.06000000001865, "steps": 2500, "solved": false, "synops": 0, "wall_time_s": 0.045835256576538086, "config": {"num_train": 100, "num_test": 50, "max_steps": 2500, "reward_shaping": true, "visit_penalty": true, "wall_bump_cost": -0.3, "hazard_cost": -1.0, "goal_reward": 10.0, "code_hash": "fe0b8142940e55de"}, "lib_version": "v2"}, {"agent_name": "TabularQ_v2", "maze_size": 25, "seed": 42, "phase": "train", "episode": 48, "reward": -212.9199999999994, "steps": 1386, "solved": true, "synops": 0, "wall_time_s": 0.019953012466430664, "config": {"num_train": 100, "num_test": 50, "max_steps": 2500, "reward_shaping": true, "visit_penalty": true, "wall_bump_cost": -0.3, "hazard_cost": -1.0, "goal_reward": 10.0, "code_hash": "fe0b8142940e55de"}, "lib_version": "v2"}, {"agent_name": "TabularQ_v2", "maze_size": 25, "seed": 42, "phase": "train", "episode": 49, "reward": -383.8400000000149, "steps": 2500, "solved": false, "synops": 0, "wall_time_s": 0.0487368106842041, "config": {"num_train": 100, "num_test": 50, "max_steps": 2500, "reward_shaping": true, "visit_penalty": true, "wall_bump_cost": -0.3, "hazard_cost": -1.0, "goal_reward": 10.0, "code_hash": "fe0b8142940e55de"}, "lib_version": "v2"}, {"agent_name": "TabularQ_v2", "maze_size": 25, "seed": 42, "phase": "train", "episode": 50, "reward": -396.50000000001415, "steps": 2500, "solved": false, "synops": 0, "wall_time_s": 0.05267071723937988, "config": {"num_train": 100, "num_test": 50, "max_steps": 2500, "reward_shaping": true, "visit_penalty": true, "wall_bump_cost": -0.3, "hazard_cost": -1.0, "goal_reward": 10.0, "code_hash": "fe0b8142940e55de"}, "lib_version": "v2"}, {"agent_name": "TabularQ_v2", "maze_size": 25, "seed": 42, "phase": "train", "episode": 51, "reward": -302.0800000000055, "steps": 1900, "solved": true, "synops": 0, "wall_time_s": 0.035005807876586914, "config": {"num_train": 100, "num_test": 50, "max_steps": 2500, "reward_shaping": true, "visit_penalty": true, "wall_bump_cost": -0.3, "hazard_cost": -1.0, "goal_reward": 10.0, "code_hash": "fe0b8142940e55de"}, "lib_version": "v2"}, {"agent_name": "TabularQ_v2", "maze_size": 25, "seed": 42, "phase": "train", "episode": 52, "reward": -386.72000000001555, "steps": 2500, "solved": false, "synops": 0, "wall_time_s": 0.05265021324157715, "config": {"num_train": 100, "num_test": 50, "max_steps": 2500, "reward_shaping": true, "visit_penalty": true, "wall_bump_cost": -0.3, "hazard_cost": -1.0, "goal_reward": 10.0, "code_hash": "fe0b8142940e55de"}, "lib_version": "v2"}, {"agent_name": "TabularQ_v2", "maze_size": 25, "seed": 42, "phase": "train", "episode": 53, "reward": -423.6800000000172, "steps": 2500, "solved": false, "synops": 0, "wall_time_s": 0.060884952545166016, "config": {"num_train": 100, "num_test": 50, "max_steps": 2500, "reward_shaping": true, "visit_penalty": true, "wall_bump_cost": -0.3, "hazard_cost": -1.0, "goal_reward": 10.0, "code_hash": "fe0b8142940e55de"}, "lib_version": "v2"}, {"agent_name": "TabularQ_v2", "maze_size": 25, "seed": 42, "phase": "train", "episode": 54, "reward": -384.280000000015, "steps": 2500, "solved": false, "synops": 0, "wall_time_s": 0.04877138137817383, "config": {"num_train": 100, "num_test": 50, "max_steps": 2500, "reward_shaping": true, "visit_penalty": true, "wall_bump_cost": -0.3, "hazard_cost": -1.0, "goal_reward": 10.0, "code_hash": "fe0b8142940e55de"}, "lib_version": "v2"}, {"agent_name": "TabularQ_v2", "maze_size": 25, "seed": 42, "phase": "train", "episode": 55, "reward": -394.960000000017, "steps": 2500, "solved": false, "synops": 0, "wall_time_s": 0.04792642593383789, "config": {"num_train": 100, "num_test": 50, "max_steps": 2500, "reward_shaping": true, "visit_penalty": true, "wall_bump_cost": -0.3, "hazard_cost": -1.0, "goal_reward": 10.0, "code_hash": "fe0b8142940e55de"}, "lib_version": "v2"}, {"agent_name": "TabularQ_v2", "maze_size": 25, "seed": 42, "phase": "train", "episode": 56, "reward": -417.8400000000177, "steps": 2500, "solved": false, "synops": 0, "wall_time_s": 0.06945013999938965, "config": {"num_train": 100, "num_test": 50, "max_steps": 2500, "reward_shaping": true, "visit_penalty": true, "wall_bump_cost": -0.3, "hazard_cost": -1.0, "goal_reward": 10.0, "code_hash": "fe0b8142940e55de"}, "lib_version": "v2"}, {"agent_name": "TabularQ_v2", "maze_size": 25, "seed": 42, "phase": "train", "episode": 57, "reward": -391.74000000001587, "steps": 2500, "solved": false, "synops": 0, "wall_time_s": 0.06221747398376465, "config": {"num_train": 100, "num_test": 50, "max_steps": 2500, "reward_shaping": true, "visit_penalty": true, "wall_bump_cost": -0.3, "hazard_cost": -1.0, "goal_reward": 10.0, "code_hash": "fe0b8142940e55de"}, "lib_version": "v2"}, {"agent_name": "TabularQ_v2", "maze_size": 25, "seed": 42, "phase": "train", "episode": 58, "reward": -385.5400000000154, "steps": 2500, "solved": false, "synops": 0, "wall_time_s": 0.08113503456115723, "config": {"num_train": 100, "num_test": 50, "max_steps": 2500, "reward_shaping": true, "visit_penalty": true, "wall_bump_cost": -0.3, "hazard_cost": -1.0, "goal_reward": 10.0, "code_hash": "fe0b8142940e55de"}, "lib_version": "v2"}, {"agent_name": "TabularQ_v2", "maze_size": 25, "seed": 42, "phase": "train", "episode": 59, "reward": -387.8600000000152, "steps": 2500, "solved": false, "synops": 0, "wall_time_s": 0.04639077186584473, "config": {"num_train": 100, "num_test": 50, "max_steps": 2500, "reward_shaping": true, "visit_penalty": true, "wall_bump_cost": -0.3, "hazard_cost": -1.0, "goal_reward": 10.0, "code_hash": "fe0b8142940e55de"}, "lib_version": "v2"}, {"agent_name": "TabularQ_v2", "maze_size": 25, "seed": 42, "phase": "train", "episode": 60, "reward": -433.5400000000184, "steps": 2500, "solved": false, "synops": 0, "wall_time_s": 0.061507225036621094, "config": {"num_train": 100, "num_test": 50, "max_steps": 2500, "reward_shaping": true, "visit_penalty": true, "wall_bump_cost": -0.3, "hazard_cost": -1.0, "goal_reward": 10.0, "code_hash": "fe0b8142940e55de"}, "lib_version": "v2"}, {"agent_name": "TabularQ_v2", "maze_size": 25, "seed": 42, "phase": "train", "episode": 61, "reward": -380.78000000001475, "steps": 2500, "solved": false, "synops": 0, "wall_time_s": 0.051438331604003906, "config": {"num_train": 100, "num_test": 50, "max_steps": 2500, "reward_shaping": true, "visit_penalty": true, "wall_bump_cost": -0.3, "hazard_cost": -1.0, "goal_reward": 10.0, "code_hash": "fe0b8142940e55de"}, "lib_version": "v2"}, {"agent_name": "TabularQ_v2", "maze_size": 25, "seed": 42, "phase": "train", "episode": 62, "reward": -407.0600000000168, "steps": 2500, "solved": false, "synops": 0, "wall_time_s": 0.043797969818115234, "config": {"num_train": 100, "num_test": 50, "max_steps": 2500, "reward_shaping": true, "visit_penalty": true, "wall_bump_cost": -0.3, "hazard_cost": -1.0, "goal_reward": 10.0, "code_hash": "fe0b8142940e55de"}, "lib_version": "v2"}, {"agent_name": "TabularQ_v2", "maze_size": 25, "seed": 42, "phase": "train", "episode": 63, "reward": -295.7800000000035, "steps": 1893, "solved": true, "synops": 0, "wall_time_s": 0.03376507759094238, "config": {"num_train": 100, "num_test": 50, "max_steps": 2500, "reward_shaping": true, "visit_penalty": true, "wall_bump_cost": -0.3, "hazard_cost": -1.0, "goal_reward": 10.0, "code_hash": "fe0b8142940e55de"}, "lib_version": "v2"}, {"agent_name": "TabularQ_v2", "maze_size": 25, "seed": 42, "phase": "train", "episode": 64, "reward": -434.7800000000189, "steps": 2500, "solved": false, "synops": 0, "wall_time_s": 0.07309651374816895, "config": {"num_train": 100, "num_test": 50, "max_steps": 2500, "reward_shaping": true, "visit_penalty": true, "wall_bump_cost": -0.3, "hazard_cost": -1.0, "goal_reward": 10.0, "code_hash": "fe0b8142940e55de"}, "lib_version": "v2"}, {"agent_name": "TabularQ_v2", "maze_size": 25, "seed": 42, "phase": "train", "episode": 65, "reward": -432.04000000001906, "steps": 2500, "solved": false, "synops": 0, "wall_time_s": 0.1851656436920166, "config": {"num_train": 100, "num_test": 50, "max_steps": 2500, "reward_shaping": true, "visit_penalty": true, "wall_bump_cost": -0.3, "hazard_cost": -1.0, "goal_reward": 10.0, "code_hash": "fe0b8142940e55de"}, "lib_version": "v2"}, {"agent_name": "TabularQ_v2", "maze_size": 25, "seed": 42, "phase": "train", "episode": 66, "reward": -398.9000000000161, "steps": 2500, "solved": false, "synops": 0, "wall_time_s": 0.22167730331420898, "config": {"num_train": 100, "num_test": 50, "max_steps": 2500, "reward_shaping": true, "visit_penalty": true, "wall_bump_cost": -0.3, "hazard_cost": -1.0, "goal_reward": 10.0, "code_hash": "fe0b8142940e55de"}, "lib_version": "v2"}, {"agent_name": "TabularQ_v2", "maze_size": 25, "seed": 42, "phase": "train", "episode": 67, "reward": -430.5200000000206, "steps": 2500, "solved": false, "synops": 0, "wall_time_s": 0.30225563049316406, "config": {"num_train": 100, "num_test": 50, "max_steps": 2500, "reward_shaping": true, "visit_penalty": true, "wall_bump_cost": -0.3, "hazard_cost": -1.0, "goal_reward": 10.0, "code_hash": "fe0b8142940e55de"}, "lib_version": "v2"}, {"agent_name": "TabularQ_v2", "maze_size": 25, "seed": 42, "phase": "train", "episode": 68, "reward": -412.30000000001775, "steps": 2500, "solved": false, "synops": 0, "wall_time_s": 0.3857920169830322, "config": {"num_train": 100, "num_test": 50, "max_steps": 2500, "reward_shaping": true, "visit_penalty": true, "wall_bump_cost": -0.3, "hazard_cost": -1.0, "goal_reward": 10.0, "code_hash": "fe0b8142940e55de"}, "lib_version": "v2"}, {"agent_name": "TabularQ_v2", "maze_size": 25, "seed": 42, "phase": "train", "episode": 69, "reward": -407.6000000000177, "steps": 2500, "solved": false, "synops": 0, "wall_time_s": 0.30505895614624023, "config": {"num_train": 100, "num_test": 50, "max_steps": 2500, "reward_shaping": true, "visit_penalty": true, "wall_bump_cost": -0.3, "hazard_cost": -1.0, "goal_reward": 10.0, "code_hash": "fe0b8142940e55de"}, "lib_version": "v2"}, {"agent_name": "TabularQ_v2", "maze_size": 25, "seed": 42, "phase": "train", "episode": 70, "reward": -395.58000000001635, "steps": 2500, "solved": false, "synops": 0, "wall_time_s": 0.4135916233062744, "config": {"num_train": 100, "num_test": 50, "max_steps": 2500, "reward_shaping": true, "visit_penalty": true, "wall_bump_cost": -0.3, "hazard_cost": -1.0, "goal_reward": 10.0, "code_hash": "fe0b8142940e55de"}, "lib_version": "v2"}, {"agent_name": "TabularQ_v2", "maze_size": 25, "seed": 42, "phase": "train", "episode": 71, "reward": -421.00000000001756, "steps": 2500, "solved": false, "synops": 0, "wall_time_s": 0.3167567253112793, "config": {"num_train": 100, "num_test": 50, "max_steps": 2500, "reward_shaping": true, "visit_penalty": true, "wall_bump_cost": -0.3, "hazard_cost": -1.0, "goal_reward": 10.0, "code_hash": "fe0b8142940e55de"}, "lib_version": "v2"}, {"agent_name": "TabularQ_v2", "maze_size": 25, "seed": 42, "phase": "train", "episode": 72, "reward": -119.21999999999957, "steps": 734, "solved": true, "synops": 0, "wall_time_s": 0.0944981575012207, "config": {"num_train": 100, "num_test": 50, "max_steps": 2500, "reward_shaping": true, "visit_penalty": true, "wall_bump_cost": -0.3, "hazard_cost": -1.0, "goal_reward": 10.0, "code_hash": "fe0b8142940e55de"}, "lib_version": "v2"}, {"agent_name": "TabularQ_v2", "maze_size": 25, "seed": 42, "phase": "train", "episode": 73, "reward": -409.5000000000165, "steps": 2500, "solved": false, "synops": 0, "wall_time_s": 0.2193608283996582, "config": {"num_train": 100, "num_test": 50, "max_steps": 2500, "reward_shaping": true, "visit_penalty": true, "wall_bump_cost": -0.3, "hazard_cost": -1.0, "goal_reward": 10.0, "code_hash": "fe0b8142940e55de"}, "lib_version": "v2"}, {"agent_name": "TabularQ_v2", "maze_size": 25, "seed": 42, "phase": "train", "episode": 74, "reward": -408.8400000000168, "steps": 2500, "solved": false, "synops": 0, "wall_time_s": 0.09447193145751953, "config": {"num_train": 100, "num_test": 50, "max_steps": 2500, "reward_shaping": true, "visit_penalty": true, "wall_bump_cost": -0.3, "hazard_cost": -1.0, "goal_reward": 10.0, "code_hash": "fe0b8142940e55de"}, "lib_version": "v2"}, {"agent_name": "TabularQ_v2", "maze_size": 25, "seed": 42, "phase": "train", "episode": 75, "reward": -409.84000000001623, "steps": 2500, "solved": false, "synops": 0, "wall_time_s": 0.10891580581665039, "config": {"num_train": 100, "num_test": 50, "max_steps": 2500, "reward_shaping": true, "visit_penalty": true, "wall_bump_cost": -0.3, "hazard_cost": -1.0, "goal_reward": 10.0, "code_hash": "fe0b8142940e55de"}, "lib_version": "v2"}, {"agent_name": "TabularQ_v2", "maze_size": 25, "seed": 42, "phase": "train", "episode": 76, "reward": -449.3600000000193, "steps": 2500, "solved": false, "synops": 0, "wall_time_s": 0.08272194862365723, "config": {"num_train": 100, "num_test": 50, "max_steps": 2500, "reward_shaping": true, "visit_penalty": true, "wall_bump_cost": -0.3, "hazard_cost": -1.0, "goal_reward": 10.0, "code_hash": "fe0b8142940e55de"}, "lib_version": "v2"}, {"agent_name": "TabularQ_v2", "maze_size": 25, "seed": 42, "phase": "train", "episode": 77, "reward": -403.1200000000166, "steps": 2500, "solved": false, "synops": 0, "wall_time_s": 0.08443903923034668, "config": {"num_train": 100, "num_test": 50, "max_steps": 2500, "reward_shaping": true, "visit_penalty": true, "wall_bump_cost": -0.3, "hazard_cost": -1.0, "goal_reward": 10.0, "code_hash": "fe0b8142940e55de"}, "lib_version": "v2"}, {"agent_name": "TabularQ_v2", "maze_size": 25, "seed": 42, "phase": "train", "episode": 78, "reward": -382.3800000000147, "steps": 2500, "solved": false, "synops": 0, "wall_time_s": 0.10183596611022949, "config": {"num_train": 100, "num_test": 50, "max_steps": 2500, "reward_shaping": true, "visit_penalty": true, "wall_bump_cost": -0.3, "hazard_cost": -1.0, "goal_reward": 10.0, "code_hash": "fe0b8142940e55de"}, "lib_version": "v2"}, {"agent_name": "TabularQ_v2", "maze_size": 25, "seed": 42, "phase": "train", "episode": 79, "reward": -394.80000000001604, "steps": 2500, "solved": false, "synops": 0, "wall_time_s": 0.10762882232666016, "config": {"num_train": 100, "num_test": 50, "max_steps": 2500, "reward_shaping": true, "visit_penalty": true, "wall_bump_cost": -0.3, "hazard_cost": -1.0, "goal_reward": 10.0, "code_hash": "fe0b8142940e55de"}, "lib_version": "v2"}, {"agent_name": "TabularQ_v2", "maze_size": 25, "seed": 42, "phase": "train", "episode": 80, "reward": -386.5200000000155, "steps": 2500, "solved": false, "synops": 0, "wall_time_s": 0.08206892013549805, "config": {"num_train": 100, "num_test": 50, "max_steps": 2500, "reward_shaping": true, "visit_penalty": true, "wall_bump_cost": -0.3, "hazard_cost": -1.0, "goal_reward": 10.0, "code_hash": "fe0b8142940e55de"}, "lib_version": "v2"}, {"agent_name": "TabularQ_v2", "maze_size": 25, "seed": 42, "phase": "train", "episode": 81, "reward": -383.20000000001494, "steps": 2500, "solved": false, "synops": 0, "wall_time_s": 0.08831977844238281, "config": {"num_train": 100, "num_test": 50, "max_steps": 2500, "reward_shaping": true, "visit_penalty": true, "wall_bump_cost": -0.3, "hazard_cost": -1.0, "goal_reward": 10.0, "code_hash": "fe0b8142940e55de"}, "lib_version": "v2"}, {"agent_name": "TabularQ_v2", "maze_size": 25, "seed": 42, "phase": "train", "episode": 82, "reward": -383.1000000000151, "steps": 2500, "solved": false, "synops": 0, "wall_time_s": 0.08305025100708008, "config": {"num_train": 100, "num_test": 50, "max_steps": 2500, "reward_shaping": true, "visit_penalty": true, "wall_bump_cost": -0.3, "hazard_cost": -1.0, "goal_reward": 10.0, "code_hash": "fe0b8142940e55de"}, "lib_version": "v2"}, {"agent_name": "TabularQ_v2", "maze_size": 25, "seed": 42, "phase": "train", "episode": 83, "reward": -397.12000000001524, "steps": 2500, "solved": false, "synops": 0, "wall_time_s": 0.08704924583435059, "config": {"num_train": 100, "num_test": 50, "max_steps": 2500, "reward_shaping": true, "visit_penalty": true, "wall_bump_cost": -0.3, "hazard_cost": -1.0, "goal_reward": 10.0, "code_hash": "fe0b8142940e55de"}, "lib_version": "v2"}, {"agent_name": "TabularQ_v2", "maze_size": 25, "seed": 42, "phase": "train", "episode": 84, "reward": -315.5600000000071, "steps": 2109, "solved": true, "synops": 0, "wall_time_s": 0.07901906967163086, "config": {"num_train": 100, "num_test": 50, "max_steps": 2500, "reward_shaping": true, "visit_penalty": true, "wall_bump_cost": -0.3, "hazard_cost": -1.0, "goal_reward": 10.0, "code_hash": "fe0b8142940e55de"}, "lib_version": "v2"}, {"agent_name": "TabularQ_v2", "maze_size": 25, "seed": 42, "phase": "train", "episode": 85, "reward": -384.24000000001564, "steps": 2500, "solved": false, "synops": 0, "wall_time_s": 0.0850679874420166, "config": {"num_train": 100, "num_test": 50, "max_steps": 2500, "reward_shaping": true, "visit_penalty": true, "wall_bump_cost": -0.3, "hazard_cost": -1.0, "goal_reward": 10.0, "code_hash": "fe0b8142940e55de"}, "lib_version": "v2"}, {"agent_name": "TabularQ_v2", "maze_size": 25, "seed": 42, "phase": "train", "episode": 86, "reward": -394.0200000000133, "steps": 2500, "solved": false, "synops": 0, "wall_time_s": 0.06546211242675781, "config": {"num_train": 100, "num_test": 50, "max_steps": 2500, "reward_shaping": true, "visit_penalty": true, "wall_bump_cost": -0.3, "hazard_cost": -1.0, "goal_reward": 10.0, "code_hash": "fe0b8142940e55de"}, "lib_version": "v2"}, {"agent_name": "TabularQ_v2", "maze_size": 25, "seed": 42, "phase": "train", "episode": 87, "reward": -407.48000000001764, "steps": 2500, "solved": false, "synops": 0, "wall_time_s": 0.08112859725952148, "config": {"num_train": 100, "num_test": 50, "max_steps": 2500, "reward_shaping": true, "visit_penalty": true, "wall_bump_cost": -0.3, "hazard_cost": -1.0, "goal_reward": 10.0, "code_hash": "fe0b8142940e55de"}, "lib_version": "v2"}, {"agent_name": "TabularQ_v2", "maze_size": 25, "seed": 42, "phase": "train", "episode": 88, "reward": -88.73999999999951, "steps": 523, "solved": true, "synops": 0, "wall_time_s": 0.01674795150756836, "config": {"num_train": 100, "num_test": 50, "max_steps": 2500, "reward_shaping": true, "visit_penalty": true, "wall_bump_cost": -0.3, "hazard_cost": -1.0, "goal_reward": 10.0, "code_hash": "fe0b8142940e55de"}, "lib_version": "v2"}, {"agent_name": "TabularQ_v2", "maze_size": 25, "seed": 42, "phase": "train", "episode": 89, "reward": -382.9000000000147, "steps": 2500, "solved": false, "synops": 0, "wall_time_s": 0.0648350715637207, "config": {"num_train": 100, "num_test": 50, "max_steps": 2500, "reward_shaping": true, "visit_penalty": true, "wall_bump_cost": -0.3, "hazard_cost": -1.0, "goal_reward": 10.0, "code_hash": "fe0b8142940e55de"}, "lib_version": "v2"}, {"agent_name": "TabularQ_v2", "maze_size": 25, "seed": 42, "phase": "train", "episode": 90, "reward": -386.8200000000156, "steps": 2500, "solved": false, "synops": 0, "wall_time_s": 0.09689712524414062, "config": {"num_train": 100, "num_test": 50, "max_steps": 2500, "reward_shaping": true, "visit_penalty": true, "wall_bump_cost": -0.3, "hazard_cost": -1.0, "goal_reward": 10.0, "code_hash": "fe0b8142940e55de"}, "lib_version": "v2"}, {"agent_name": "TabularQ_v2", "maze_size": 25, "seed": 42, "phase": "train", "episode": 91, "reward": -418.16000000001935, "steps": 2500, "solved": false, "synops": 0, "wall_time_s": 0.07847452163696289, "config": {"num_train": 100, "num_test": 50, "max_steps": 2500, "reward_shaping": true, "visit_penalty": true, "wall_bump_cost": -0.3, "hazard_cost": -1.0, "goal_reward": 10.0, "code_hash": "fe0b8142940e55de"}, "lib_version": "v2"}, {"agent_name": "TabularQ_v2", "maze_size": 25, "seed": 42, "phase": "train", "episode": 92, "reward": -412.78000000001686, "steps": 2500, "solved": false, "synops": 0, "wall_time_s": 0.0657498836517334, "config": {"num_train": 100, "num_test": 50, "max_steps": 2500, "reward_shaping": true, "visit_penalty": true, "wall_bump_cost": -0.3, "hazard_cost": -1.0, "goal_reward": 10.0, "code_hash": "fe0b8142940e55de"}, "lib_version": "v2"}, {"agent_name": "TabularQ_v2", "maze_size": 25, "seed": 42, "phase": "train", "episode": 93, "reward": -406.22000000001646, "steps": 2500, "solved": false, "synops": 0, "wall_time_s": 0.07669353485107422, "config": {"num_train": 100, "num_test": 50, "max_steps": 2500, "reward_shaping": true, "visit_penalty": true, "wall_bump_cost": -0.3, "hazard_cost": -1.0, "goal_reward": 10.0, "code_hash": "fe0b8142940e55de"}, "lib_version": "v2"}, {"agent_name": "TabularQ_v2", "maze_size": 25, "seed": 42, "phase": "train", "episode": 94, "reward": -386.22000000001566, "steps": 2500, "solved": false, "synops": 0, "wall_time_s": 0.07581210136413574, "config": {"num_train": 100, "num_test": 50, "max_steps": 2500, "reward_shaping": true, "visit_penalty": true, "wall_bump_cost": -0.3, "hazard_cost": -1.0, "goal_reward": 10.0, "code_hash": "fe0b8142940e55de"}, "lib_version": "v2"}, {"agent_name": "TabularQ_v2", "maze_size": 25, "seed": 42, "phase": "train", "episode": 95, "reward": -403.040000000016, "steps": 2500, "solved": false, "synops": 0, "wall_time_s": 0.0698707103729248, "config": {"num_train": 100, "num_test": 50, "max_steps": 2500, "reward_shaping": true, "visit_penalty": true, "wall_bump_cost": -0.3, "hazard_cost": -1.0, "goal_reward": 10.0, "code_hash": "fe0b8142940e55de"}, "lib_version": "v2"}, {"agent_name": "TabularQ_v2", "maze_size": 25, "seed": 42, "phase": "train", "episode": 96, "reward": -214.67999999999887, "steps": 1383, "solved": true, "synops": 0, "wall_time_s": 0.048178911209106445, "config": {"num_train": 100, "num_test": 50, "max_steps": 2500, "reward_shaping": true, "visit_penalty": true, "wall_bump_cost": -0.3, "hazard_cost": -1.0, "goal_reward": 10.0, "code_hash": "fe0b8142940e55de"}, "lib_version": "v2"}, {"agent_name": "TabularQ_v2", "maze_size": 25, "seed": 42, "phase": "train", "episode": 97, "reward": -123.73999999999944, "steps": 855, "solved": true, "synops": 0, "wall_time_s": 0.028655290603637695, "config": {"num_train": 100, "num_test": 50, "max_steps": 2500, "reward_shaping": true, "visit_penalty": true, "wall_bump_cost": -0.3, "hazard_cost": -1.0, "goal_reward": 10.0, "code_hash": "fe0b8142940e55de"}, "lib_version": "v2"}, {"agent_name": "TabularQ_v2", "maze_size": 25, "seed": 42, "phase": "train", "episode": 98, "reward": -156.23999999999987, "steps": 1068, "solved": true, "synops": 0, "wall_time_s": 0.03862118721008301, "config": {"num_train": 100, "num_test": 50, "max_steps": 2500, "reward_shaping": true, "visit_penalty": true, "wall_bump_cost": -0.3, "hazard_cost": -1.0, "goal_reward": 10.0, "code_hash": "fe0b8142940e55de"}, "lib_version": "v2"}, {"agent_name": "TabularQ_v2", "maze_size": 25, "seed": 42, "phase": "train", "episode": 99, "reward": -400.86000000001616, "steps": 2500, "solved": false, "synops": 0, "wall_time_s": 0.07099366188049316, "config": {"num_train": 100, "num_test": 50, "max_steps": 2500, "reward_shaping": true, "visit_penalty": true, "wall_bump_cost": -0.3, "hazard_cost": -1.0, "goal_reward": 10.0, "code_hash": "fe0b8142940e55de"}, "lib_version": "v2"}, {"agent_name": "TabularQ_v2", "maze_size": 25, "seed": 42, "phase": "test", "episode": 0, "reward": -747.7599999999779, "steps": 2500, "solved": false, "synops": 0, "wall_time_s": 0.032918691635131836, "config": {"num_train": 100, "num_test": 50, "max_steps": 2500, "reward_shaping": true, "visit_penalty": true, "wall_bump_cost": -0.3, "hazard_cost": -1.0, "goal_reward": 10.0, "code_hash": "fe0b8142940e55de"}, "lib_version": "v2"}, {"agent_name": "TabularQ_v2", "maze_size": 25, "seed": 42, "phase": "test", "episode": 1, "reward": -249.11999999999327, "steps": 2500, "solved": false, "synops": 0, "wall_time_s": 0.047251224517822266, "config": {"num_train": 100, "num_test": 50, "max_steps": 2500, "reward_shaping": true, "visit_penalty": true, "wall_bump_cost": -0.3, "hazard_cost": -1.0, "goal_reward": 10.0, "code_hash": "fe0b8142940e55de"}, "lib_version": "v2"}, {"agent_name": "TabularQ_v2", "maze_size": 25, "seed": 42, "phase": "test", "episode": 2, "reward": -778.8799999999825, "steps": 2500, "solved": false, "synops": 0, "wall_time_s": 0.03438615798950195, "config": {"num_train": 100, "num_test": 50, "max_steps": 2500, "reward_shaping": true, "visit_penalty": true, "wall_bump_cost": -0.3, "hazard_cost": -1.0, "goal_reward": 10.0, "code_hash": "fe0b8142940e55de"}, "lib_version": "v2"}, {"agent_name": "TabularQ_v2", "maze_size": 25, "seed": 42, "phase": "test", "episode": 3, "reward": -249.89999999999324, "steps": 2500, "solved": false, "synops": 0, "wall_time_s": 0.04115772247314453, "config": {"num_train": 100, "num_test": 50, "max_steps": 2500, "reward_shaping": true, "visit_penalty": true, "wall_bump_cost": -0.3, "hazard_cost": -1.0, "goal_reward": 10.0, "code_hash": "fe0b8142940e55de"}, "lib_version": "v2"}, {"agent_name": "TabularQ_v2", "maze_size": 25, "seed": 42, "phase": "test", "episode": 4, "reward": -249.89999999999324, "steps": 2500, "solved": false, "synops": 0, "wall_time_s": 0.04440569877624512, "config": {"num_train": 100, "num_test": 50, "max_steps": 2500, "reward_shaping": true, "visit_penalty": true, "wall_bump_cost": -0.3, "hazard_cost": -1.0, "goal_reward": 10.0, "code_hash": "fe0b8142940e55de"}, "lib_version": "v2"}, {"agent_name": "TabularQ_v2", "maze_size": 25, "seed": 42, "phase": "test", "episode": 5, "reward": -687.9799999999898, "steps": 2500, "solved": false, "synops": 0, "wall_time_s": 0.03880429267883301, "config": {"num_train": 100, "num_test": 50, "max_steps": 2500, "reward_shaping": true, "visit_penalty": true, "wall_bump_cost": -0.3, "hazard_cost": -1.0, "goal_reward": 10.0, "code_hash": "fe0b8142940e55de"}, "lib_version": "v2"}, {"agent_name": "TabularQ_v2", "maze_size": 25, "seed": 42, "phase": "test", "episode": 6, "reward": -249.89999999999324, "steps": 2500, "solved": false, "synops": 0, "wall_time_s": 0.04179239273071289, "config": {"num_train": 100, "num_test": 50, "max_steps": 2500, "reward_shaping": true, "visit_penalty": true, "wall_bump_cost": -0.3, "hazard_cost": -1.0, "goal_reward": 10.0, "code_hash": "fe0b8142940e55de"}, "lib_version": "v2"}, {"agent_name": "TabularQ_v2", "maze_size": 25, "seed": 42, "phase": "test", "episode": 7, "reward": -427.3200000000184, "steps": 2500, "solved": false, "synops": 0, "wall_time_s": 0.035327911376953125, "config": {"num_train": 100, "num_test": 50, "max_steps": 2500, "reward_shaping": true, "visit_penalty": true, "wall_bump_cost": -0.3, "hazard_cost": -1.0, "goal_reward": 10.0, "code_hash": "fe0b8142940e55de"}, "lib_version": "v2"}, {"agent_name": "TabularQ_v2", "maze_size": 25, "seed": 42, "phase": "test", "episode": 8, "reward": -748.5599999999778, "steps": 2500, "solved": false, "synops": 0, "wall_time_s": 0.044065237045288086, "config": {"num_train": 100, "num_test": 50, "max_steps": 2500, "reward_shaping": true, "visit_penalty": true, "wall_bump_cost": -0.3, "hazard_cost": -1.0, "goal_reward": 10.0, "code_hash": "fe0b8142940e55de"}, "lib_version": "v2"}, {"agent_name": "TabularQ_v2", "maze_size": 25, "seed": 42, "phase": "test", "episode": 9, "reward": -740.959999999979, "steps": 2500, "solved": false, "synops": 0, "wall_time_s": 0.040624141693115234, "config": {"num_train": 100, "num_test": 50, "max_steps": 2500, "reward_shaping": true, "visit_penalty": true, "wall_bump_cost": -0.3, "hazard_cost": -1.0, "goal_reward": 10.0, "code_hash": "fe0b8142940e55de"}, "lib_version": "v2"}, {"agent_name": "TabularQ_v2", "maze_size": 25, "seed": 42, "phase": "test", "episode": 10, "reward": -249.89999999999324, "steps": 2500, "solved": false, "synops": 0, "wall_time_s": 0.0474696159362793, "config": {"num_train": 100, "num_test": 50, "max_steps": 2500, "reward_shaping": true, "visit_penalty": true, "wall_bump_cost": -0.3, "hazard_cost": -1.0, "goal_reward": 10.0, "code_hash": "fe0b8142940e55de"}, "lib_version": "v2"}, {"agent_name": "TabularQ_v2", "maze_size": 25, "seed": 42, "phase": "test", "episode": 11, "reward": -748.1599999999779, "steps": 2500, "solved": false, "synops": 0, "wall_time_s": 0.0430908203125, "config": {"num_train": 100, "num_test": 50, "max_steps": 2500, "reward_shaping": true, "visit_penalty": true, "wall_bump_cost": -0.3, "hazard_cost": -1.0, "goal_reward": 10.0, "code_hash": "fe0b8142940e55de"}, "lib_version": "v2"}, {"agent_name": "TabularQ_v2", "maze_size": 25, "seed": 42, "phase": "test", "episode": 12, "reward": -745.3199999999783, "steps": 2500, "solved": false, "synops": 0, "wall_time_s": 0.04179644584655762, "config": {"num_train": 100, "num_test": 50, "max_steps": 2500, "reward_shaping": true, "visit_penalty": true, "wall_bump_cost": -0.3, "hazard_cost": -1.0, "goal_reward": 10.0, "code_hash": "fe0b8142940e55de"}, "lib_version": "v2"}, {"agent_name": "TabularQ_v2", "maze_size": 25, "seed": 42, "phase": "test", "episode": 13, "reward": -744.4999999999784, "steps": 2500, "solved": false, "synops": 0, "wall_time_s": 0.07538580894470215, "config": {"num_train": 100, "num_test": 50, "max_steps": 2500, "reward_shaping": true, "visit_penalty": true, "wall_bump_cost": -0.3, "hazard_cost": -1.0, "goal_reward": 10.0, "code_hash": "fe0b8142940e55de"}, "lib_version": "v2"}, {"agent_name": "TabularQ_v2", "maze_size": 25, "seed": 42, "phase": "test", "episode": 14, "reward": -249.89999999999324, "steps": 2500, "solved": false, "synops": 0, "wall_time_s": 0.04953932762145996, "config": {"num_train": 100, "num_test": 50, "max_steps": 2500, "reward_shaping": true, "visit_penalty": true, "wall_bump_cost": -0.3, "hazard_cost": -1.0, "goal_reward": 10.0, "code_hash": "fe0b8142940e55de"}, "lib_version": "v2"}, {"agent_name": "TabularQ_v2", "maze_size": 25, "seed": 42, "phase": "test", "episode": 15, "reward": -557.640000000012, "steps": 2500, "solved": false, "synops": 0, "wall_time_s": 0.04402351379394531, "config": {"num_train": 100, "num_test": 50, "max_steps": 2500, "reward_shaping": true, "visit_penalty": true, "wall_bump_cost": -0.3, "hazard_cost": -1.0, "goal_reward": 10.0, "code_hash": "fe0b8142940e55de"}, "lib_version": "v2"}, {"agent_name": "TabularQ_v2", "maze_size": 25, "seed": 42, "phase": "test", "episode": 16, "reward": -746.2399999999782, "steps": 2500, "solved": false, "synops": 0, "wall_time_s": 0.05307149887084961, "config": {"num_train": 100, "num_test": 50, "max_steps": 2500, "reward_shaping": true, "visit_penalty": true, "wall_bump_cost": -0.3, "hazard_cost": -1.0, "goal_reward": 10.0, "code_hash": "fe0b8142940e55de"}, "lib_version": "v2"}, {"agent_name": "TabularQ_v2", "maze_size": 25, "seed": 42, "phase": "test", "episode": 17, "reward": -741.2399999999789, "steps": 2500, "solved": false, "synops": 0, "wall_time_s": 0.029680252075195312, "config": {"num_train": 100, "num_test": 50, "max_steps": 2500, "reward_shaping": true, "visit_penalty": true, "wall_bump_cost": -0.3, "hazard_cost": -1.0, "goal_reward": 10.0, "code_hash": "fe0b8142940e55de"}, "lib_version": "v2"}, {"agent_name": "TabularQ_v2", "maze_size": 25, "seed": 42, "phase": "test", "episode": 18, "reward": -748.5599999999778, "steps": 2500, "solved": false, "synops": 0, "wall_time_s": 0.03165125846862793, "config": {"num_train": 100, "num_test": 50, "max_steps": 2500, "reward_shaping": true, "visit_penalty": true, "wall_bump_cost": -0.3, "hazard_cost": -1.0, "goal_reward": 10.0, "code_hash": "fe0b8142940e55de"}, "lib_version": "v2"}, {"agent_name": "TabularQ_v2", "maze_size": 25, "seed": 42, "phase": "test", "episode": 19, "reward": -251.93999999999312, "steps": 2500, "solved": false, "synops": 0, "wall_time_s": 0.04483294486999512, "config": {"num_train": 100, "num_test": 50, "max_steps": 2500, "reward_shaping": true, "visit_penalty": true, "wall_bump_cost": -0.3, "hazard_cost": -1.0, "goal_reward": 10.0, "code_hash": "fe0b8142940e55de"}, "lib_version": "v2"}, {"agent_name": "TabularQ_v2", "maze_size": 25, "seed": 42, "phase": "test", "episode": 20, "reward": -737.9799999999794, "steps": 2500, "solved": false, "synops": 0, "wall_time_s": 0.036092281341552734, "config": {"num_train": 100, "num_test": 50, "max_steps": 2500, "reward_shaping": true, "visit_penalty": true, "wall_bump_cost": -0.3, "hazard_cost": -1.0, "goal_reward": 10.0, "code_hash": "fe0b8142940e55de"}, "lib_version": "v2"}, {"agent_name": "TabularQ_v2", "maze_size": 25, "seed": 42, "phase": "test", "episode": 21, "reward": -742.5599999999787, "steps": 2500, "solved": false, "synops": 0, "wall_time_s": 0.02932286262512207, "config": {"num_train": 100, "num_test": 50, "max_steps": 2500, "reward_shaping": true, "visit_penalty": true, "wall_bump_cost": -0.3, "hazard_cost": -1.0, "goal_reward": 10.0, "code_hash": "fe0b8142940e55de"}, "lib_version": "v2"}, {"agent_name": "TabularQ_v2", "maze_size": 25, "seed": 42, "phase": "test", "episode": 22, "reward": -749.2799999999777, "steps": 2500, "solved": false, "synops": 0, "wall_time_s": 0.03220033645629883, "config": {"num_train": 100, "num_test": 50, "max_steps": 2500, "reward_shaping": true, "visit_penalty": true, "wall_bump_cost": -0.3, "hazard_cost": -1.0, "goal_reward": 10.0, "code_hash": "fe0b8142940e55de"}, "lib_version": "v2"}, {"agent_name": "TabularQ_v2", "maze_size": 25, "seed": 42, "phase": "test", "episode": 23, "reward": -466.2600000000198, "steps": 2500, "solved": false, "synops": 0, "wall_time_s": 0.027149438858032227, "config": {"num_train": 100, "num_test": 50, "max_steps": 2500, "reward_shaping": true, "visit_penalty": true, "wall_bump_cost": -0.3, "hazard_cost": -1.0, "goal_reward": 10.0, "code_hash": "fe0b8142940e55de"}, "lib_version": "v2"}, {"agent_name": "TabularQ_v2", "maze_size": 25, "seed": 42, "phase": "test", "episode": 24, "reward": -695.4999999999905, "steps": 2500, "solved": false, "synops": 0, "wall_time_s": 0.023361921310424805, "config": {"num_train": 100, "num_test": 50, "max_steps": 2500, "reward_shaping": true, "visit_penalty": true, "wall_bump_cost": -0.3, "hazard_cost": -1.0, "goal_reward": 10.0, "code_hash": "fe0b8142940e55de"}, "lib_version": "v2"}, {"agent_name": "TabularQ_v2", "maze_size": 25, "seed": 42, "phase": "test", "episode": 25, "reward": -249.27999999999327, "steps": 2500, "solved": false, "synops": 0, "wall_time_s": 0.03865361213684082, "config": {"num_train": 100, "num_test": 50, "max_steps": 2500, "reward_shaping": true, "visit_penalty": true, "wall_bump_cost": -0.3, "hazard_cost": -1.0, "goal_reward": 10.0, "code_hash": "fe0b8142940e55de"}, "lib_version": "v2"}, {"agent_name": "TabularQ_v2", "maze_size": 25, "seed": 42, "phase": "test", "episode": 26, "reward": -745.8399999999782, "steps": 2500, "solved": false, "synops": 0, "wall_time_s": 0.03790616989135742, "config": {"num_train": 100, "num_test": 50, "max_steps": 2500, "reward_shaping": true, "visit_penalty": true, "wall_bump_cost": -0.3, "hazard_cost": -1.0, "goal_reward": 10.0, "code_hash": "fe0b8142940e55de"}, "lib_version": "v2"}, {"agent_name": "TabularQ_v2", "maze_size": 25, "seed": 42, "phase": "test", "episode": 27, "reward": -475.40000000002135, "steps": 2500, "solved": false, "synops": 0, "wall_time_s": 0.04039192199707031, "config": {"num_train": 100, "num_test": 50, "max_steps": 2500, "reward_shaping": true, "visit_penalty": true, "wall_bump_cost": -0.3, "hazard_cost": -1.0, "goal_reward": 10.0, "code_hash": "fe0b8142940e55de"}, "lib_version": "v2"}, {"agent_name": "TabularQ_v2", "maze_size": 25, "seed": 42, "phase": "test", "episode": 28, "reward": -745.0399999999784, "steps": 2500, "solved": false, "synops": 0, "wall_time_s": 0.04070448875427246, "config": {"num_train": 100, "num_test": 50, "max_steps": 2500, "reward_shaping": true, "visit_penalty": true, "wall_bump_cost": -0.3, "hazard_cost": -1.0, "goal_reward": 10.0, "code_hash": "fe0b8142940e55de"}, "lib_version": "v2"}, {"agent_name": "TabularQ_v2", "maze_size": 25, "seed": 42, "phase": "test", "episode": 29, "reward": -742.7599999999787, "steps": 2500, "solved": false, "synops": 0, "wall_time_s": 0.026407241821289062, "config": {"num_train": 100, "num_test": 50, "max_steps": 2500, "reward_shaping": true, "visit_penalty": true, "wall_bump_cost": -0.3, "hazard_cost": -1.0, "goal_reward": 10.0, "code_hash": "fe0b8142940e55de"}, "lib_version": "v2"}, {"agent_name": "TabularQ_v2", "maze_size": 25, "seed": 42, "phase": "test", "episode": 30, "reward": -249.89999999999324, "steps": 2500, "solved": false, "synops": 0, "wall_time_s": 0.03377985954284668, "config": {"num_train": 100, "num_test": 50, "max_steps": 2500, "reward_shaping": true, "visit_penalty": true, "wall_bump_cost": -0.3, "hazard_cost": -1.0, "goal_reward": 10.0, "code_hash": "fe0b8142940e55de"}, "lib_version": "v2"}, {"agent_name": "TabularQ_v2", "maze_size": 25, "seed": 42, "phase": "test", "episode": 31, "reward": -249.77999999999324, "steps": 2500, "solved": false, "synops": 0, "wall_time_s": 0.03639841079711914, "config": {"num_train": 100, "num_test": 50, "max_steps": 2500, "reward_shaping": true, "visit_penalty": true, "wall_bump_cost": -0.3, "hazard_cost": -1.0, "goal_reward": 10.0, "code_hash": "fe0b8142940e55de"}, "lib_version": "v2"}, {"agent_name": "TabularQ_v2", "maze_size": 25, "seed": 42, "phase": "test", "episode": 32, "reward": -249.89999999999324, "steps": 2500, "solved": false, "synops": 0, "wall_time_s": 0.03553009033203125, "config": {"num_train": 100, "num_test": 50, "max_steps": 2500, "reward_shaping": true, "visit_penalty": true, "wall_bump_cost": -0.3, "hazard_cost": -1.0, "goal_reward": 10.0, "code_hash": "fe0b8142940e55de"}, "lib_version": "v2"}, {"agent_name": "TabularQ_v2", "maze_size": 25, "seed": 42, "phase": "test", "episode": 33, "reward": -743.3599999999786, "steps": 2500, "solved": false, "synops": 0, "wall_time_s": 0.02916884422302246, "config": {"num_train": 100, "num_test": 50, "max_steps": 2500, "reward_shaping": true, "visit_penalty": true, "wall_bump_cost": -0.3, "hazard_cost": -1.0, "goal_reward": 10.0, "code_hash": "fe0b8142940e55de"}, "lib_version": "v2"}, {"agent_name": "TabularQ_v2", "maze_size": 25, "seed": 42, "phase": "test", "episode": 34, "reward": -250.79999999999316, "steps": 2500, "solved": false, "synops": 0, "wall_time_s": 0.03228425979614258, "config": {"num_train": 100, "num_test": 50, "max_steps": 2500, "reward_shaping": true, "visit_penalty": true, "wall_bump_cost": -0.3, "hazard_cost": -1.0, "goal_reward": 10.0, "code_hash": "fe0b8142940e55de"}, "lib_version": "v2"}, {"agent_name": "TabularQ_v2", "maze_size": 25, "seed": 42, "phase": "test", "episode": 35, "reward": -249.89999999999324, "steps": 2500, "solved": false, "synops": 0, "wall_time_s": 0.033537864685058594, "config": {"num_train": 100, "num_test": 50, "max_steps": 2500, "reward_shaping": true, "visit_penalty": true, "wall_bump_cost": -0.3, "hazard_cost": -1.0, "goal_reward": 10.0, "code_hash": "fe0b8142940e55de"}, "lib_version": "v2"}, {"agent_name": "TabularQ_v2", "maze_size": 25, "seed": 42, "phase": "test", "episode": 36, "reward": -748.1599999999779, "steps": 2500, "solved": false, "synops": 0, "wall_time_s": 0.025569915771484375, "config": {"num_train": 100, "num_test": 50, "max_steps": 2500, "reward_shaping": true, "visit_penalty": true, "wall_bump_cost": -0.3, "hazard_cost": -1.0, "goal_reward": 10.0, "code_hash": "fe0b8142940e55de"}, "lib_version": "v2"}, {"agent_name": "TabularQ_v2", "maze_size": 25, "seed": 42, "phase": "test", "episode": 37, "reward": -694.7799999999905, "steps": 2500, "solved": false, "synops": 0, "wall_time_s": 0.033124446868896484, "config": {"num_train": 100, "num_test": 50, "max_steps": 2500, "reward_shaping": true, "visit_penalty": true, "wall_bump_cost": -0.3, "hazard_cost": -1.0, "goal_reward": 10.0, "code_hash": "fe0b8142940e55de"}, "lib_version": "v2"}, {"agent_name": "TabularQ_v2", "maze_size": 25, "seed": 42, "phase": "test", "episode": 38, "reward": -249.89999999999324, "steps": 2500, "solved": false, "synops": 0, "wall_time_s": 0.041867971420288086, "config": {"num_train": 100, "num_test": 50, "max_steps": 2500, "reward_shaping": true, "visit_penalty": true, "wall_bump_cost": -0.3, "hazard_cost": -1.0, "goal_reward": 10.0, "code_hash": "fe0b8142940e55de"}, "lib_version": "v2"}, {"agent_name": "TabularQ_v2", "maze_size": 25, "seed": 42, "phase": "test", "episode": 39, "reward": -251.9199999999931, "steps": 2500, "solved": false, "synops": 0, "wall_time_s": 0.03362274169921875, "config": {"num_train": 100, "num_test": 50, "max_steps": 2500, "reward_shaping": true, "visit_penalty": true, "wall_bump_cost": -0.3, "hazard_cost": -1.0, "goal_reward": 10.0, "code_hash": "fe0b8142940e55de"}, "lib_version": "v2"}, {"agent_name": "TabularQ_v2", "maze_size": 25, "seed": 42, "phase": "test", "episode": 40, "reward": -430.3800000000186, "steps": 2500, "solved": false, "synops": 0, "wall_time_s": 0.02504754066467285, "config": {"num_train": 100, "num_test": 50, "max_steps": 2500, "reward_shaping": true, "visit_penalty": true, "wall_bump_cost": -0.3, "hazard_cost": -1.0, "goal_reward": 10.0, "code_hash": "fe0b8142940e55de"}, "lib_version": "v2"}, {"agent_name": "TabularQ_v2", "maze_size": 25, "seed": 42, "phase": "test", "episode": 41, "reward": -737.3599999999796, "steps": 2500, "solved": false, "synops": 0, "wall_time_s": 0.03247857093811035, "config": {"num_train": 100, "num_test": 50, "max_steps": 2500, "reward_shaping": true, "visit_penalty": true, "wall_bump_cost": -0.3, "hazard_cost": -1.0, "goal_reward": 10.0, "code_hash": "fe0b8142940e55de"}, "lib_version": "v2"}, {"agent_name": "TabularQ_v2", "maze_size": 25, "seed": 42, "phase": "test", "episode": 42, "reward": -748.1599999999779, "steps": 2500, "solved": false, "synops": 0, "wall_time_s": 0.03528714179992676, "config": {"num_train": 100, "num_test": 50, "max_steps": 2500, "reward_shaping": true, "visit_penalty": true, "wall_bump_cost": -0.3, "hazard_cost": -1.0, "goal_reward": 10.0, "code_hash": "fe0b8142940e55de"}, "lib_version": "v2"}, {"agent_name": "TabularQ_v2", "maze_size": 25, "seed": 42, "phase": "test", "episode": 43, "reward": -249.89999999999324, "steps": 2500, "solved": false, "synops": 0, "wall_time_s": 0.04083585739135742, "config": {"num_train": 100, "num_test": 50, "max_steps": 2500, "reward_shaping": true, "visit_penalty": true, "wall_bump_cost": -0.3, "hazard_cost": -1.0, "goal_reward": 10.0, "code_hash": "fe0b8142940e55de"}, "lib_version": "v2"}, {"agent_name": "TabularQ_v2", "maze_size": 25, "seed": 42, "phase": "test", "episode": 44, "reward": -743.8399999999785, "steps": 2500, "solved": false, "synops": 0, "wall_time_s": 0.026088953018188477, "config": {"num_train": 100, "num_test": 50, "max_steps": 2500, "reward_shaping": true, "visit_penalty": true, "wall_bump_cost": -0.3, "hazard_cost": -1.0, "goal_reward": 10.0, "code_hash": "fe0b8142940e55de"}, "lib_version": "v2"}, {"agent_name": "TabularQ_v2", "maze_size": 25, "seed": 42, "phase": "test", "episode": 45, "reward": -249.89999999999324, "steps": 2500, "solved": false, "synops": 0, "wall_time_s": 0.033506155014038086, "config": {"num_train": 100, "num_test": 50, "max_steps": 2500, "reward_shaping": true, "visit_penalty": true, "wall_bump_cost": -0.3, "hazard_cost": -1.0, "goal_reward": 10.0, "code_hash": "fe0b8142940e55de"}, "lib_version": "v2"}, {"agent_name": "TabularQ_v2", "maze_size": 25, "seed": 42, "phase": "test", "episode": 46, "reward": -746.4999999999782, "steps": 2500, "solved": false, "synops": 0, "wall_time_s": 0.03270268440246582, "config": {"num_train": 100, "num_test": 50, "max_steps": 2500, "reward_shaping": true, "visit_penalty": true, "wall_bump_cost": -0.3, "hazard_cost": -1.0, "goal_reward": 10.0, "code_hash": "fe0b8142940e55de"}, "lib_version": "v2"}, {"agent_name": "TabularQ_v2", "maze_size": 25, "seed": 42, "phase": "test", "episode": 47, "reward": -744.4999999999784, "steps": 2500, "solved": false, "synops": 0, "wall_time_s": 0.033319950103759766, "config": {"num_train": 100, "num_test": 50, "max_steps": 2500, "reward_shaping": true, "visit_penalty": true, "wall_bump_cost": -0.3, "hazard_cost": -1.0, "goal_reward": 10.0, "code_hash": "fe0b8142940e55de"}, "lib_version": "v2"}, {"agent_name": "TabularQ_v2", "maze_size": 25, "seed": 42, "phase": "test", "episode": 48, "reward": -249.89999999999324, "steps": 2500, "solved": false, "synops": 0, "wall_time_s": 0.03352236747741699, "config": {"num_train": 100, "num_test": 50, "max_steps": 2500, "reward_shaping": true, "visit_penalty": true, "wall_bump_cost": -0.3, "hazard_cost": -1.0, "goal_reward": 10.0, "code_hash": "fe0b8142940e55de"}, "lib_version": "v2"}, {"agent_name": "TabularQ_v2", "maze_size": 25, "seed": 42, "phase": "test", "episode": 49, "reward": -747.8399999999779, "steps": 2500, "solved": false, "synops": 0, "wall_time_s": 0.025050640106201172, "config": {"num_train": 100, "num_test": 50, "max_steps": 2500, "reward_shaping": true, "visit_penalty": true, "wall_bump_cost": -0.3, "hazard_cost": -1.0, "goal_reward": 10.0, "code_hash": "fe0b8142940e55de"}, "lib_version": "v2"}]